[
  {
    "word": "lernen",
    "translations": {
      "fa": "یاد گرفتن",
      "en": "to learn"
    },
    "explanation": {
      "fa": "به دست آوردن دانش یا مهارت از طریق مطالعه، تمرین یا آموزش.",
      "en": "To gain knowledge or skill by studying, practicing, or being taught."
    },
    "conjugations": [
      "lernen",
      "lernt",
      "lernte",
      "hat gelernt"
    ],
    "examples": {
      "fa": [
        "Ich lerne Deutsch.",
        "من دارم آلمانی یاد می‌گیرم."
      ],
      "en": [
        "Ich lerne jeden Tag neue Wörter.",
        "I learn new words every day."
      ]
    }
  },
  {
    "word": "verstehen",
    "translations": {
      "fa": "فهمیدن",
      "en": "to understand"
    },
    "explanation": {
      "fa": "معنی یا مفهوم چیزی را دریافت کردن.",
      "en": "To grasp the meaning or concept of something."
    },
    "conjugations": [
      "verstehen",
      "versteht",
      "verstand",
      "hat verstanden"
    ],
    "examples": {
      "fa": [
        "Verstehst du die Frage?",
        "آیا سوال را می‌فهمی؟"
      ],
      "en": [
        "Ich verstehe das nicht.",
        "I don't understand that."
      ]
    }
  },
  {
    "word": "sprechen",
    "translations": {
      "fa": "صحبت کردن",
      "en": "to speak"
    },
    "explanation": {
      "fa": "به زبان آوردن کلمات؛ گفتگو کردن.",
      "en": "To say words; to communicate verbally."
    },
    "conjugations": [
      "sprechen",
      "spricht",
      "sprach",
      "hat gesprochen"
    ],
    "examples": {
      "fa": [
        "Ich spreche Deutsch und Englisch.",
        "من آلمانی و انگلیسی صحبت می‌کنم."
      ],
      "en": [
        "Kannst du bitte langsamer sprechen?",
        "Can you please speak more slowly?"
      ]
    }
  },
  {
    "word": "arbeiten",
    "translations": {
      "fa": "کار کردن",
      "en": "to work"
    },
    "explanation": {
      "fa": "انجام فعالیت برای کسب درآمد یا رسیدن به هدف.",
      "en": "To perform an activity for income or to achieve a goal."
    },
    "conjugations": [
      "arbeiten",
      "arbeitet",
      "arbeitete",
      "hat gearbeitet"
    ],
    "examples": {
      "fa": [
        "Ich arbeite bei einer Bank.",
        "من در یک بانک کار می‌کنم."
      ],
      "en": [
        "Er arbeitet von Montag bis Freitag.",
        "He works from Monday to Friday."
      ]
    }
  },
  {
    "word": "die Wohnung",
    "translations": {
      "fa": "آپارتمان",
      "en": "apartment"
    },
    "explanation": {
      "fa": "مجموعه‌ای از اتاق‌ها برای زندگی در یک ساختمان.",
      "en": "A set of rooms for living in, usually in a building."
    },
    "conjugations": null,
    "examples": {
      "fa": [
        "Ich suche eine neue Wohnung.",
        "من دنبال یک آپارتمان جدید می‌گردم."
      ],
      "en": [
        "Die Wohnung hat drei Zimmer.",
        "The apartment has three rooms."
      ]
    }
  },
  {
    "word": "der Nachbar",
    "translations": {
      "fa": "همسایه",
      "en": "neighbor"
    },
    "explanation": {
      "fa": "شخصی که در نزدیکی شما زندگی می‌کند.",
      "en": "A person who lives near you."
    },
    "conjugations": null,
    "examples": {
      "fa": [
        "Mein Nachbar ist sehr freundlich.",
        "همسایه من خیلی مهربان است."
      ],
      "en": [
        "Ich kenne meine Nachbarn gut.",
        "I know my neighbors well."
      ]
    }
  },
  {
    "word": "das Geschäft",
    "translations": {
      "fa": "فروشگاه، مغازه",
      "en": "shop, store"
    },
    "explanation": {
      "fa": "مکانی برای خرید کالا یا خدمات.",
      "en": "A place where goods or services are sold."
    },
    "conjugations": null,
    "examples": {
      "fa": [
        "Das Geschäft öffnet um 9 Uhr.",
        "فروشگاه ساعت ۹ باز می‌شود."
      ],
      "en": [
        "In diesem Geschäft kaufe ich immer ein.",
        "I always shop in this store."
      ]
    }
  },
  {
    "word": "einkaufen",
    "translations": {
      "fa": "خرید کردن",
      "en": "to shop, to buy groceries"
    },
    "explanation": {
      "fa": "خریدن کالاها، به‌ویژه مواد غذایی و ضروریات روزانه.",
      "en": "To buy goods, especially groceries and daily necessities."
    },
    "conjugations": [
      "einkaufen",
      "kauft ein",
      "kaufte ein",
      "hat eingekauft"
    ],
    "examples": {
      "fa": [
        "Ich gehe heute einkaufen.",
        "من امروز می‌روم خرید."
      ],
      "en": [
        "Wo kaufst du normalerweise ein?",
        "Where do you normally shop?"
      ]
    }
  },
  {
    "word": "bezahlen",
    "translations": {
      "fa": "پرداخت کردن",
      "en": "to pay"
    },
    "explanation": {
      "fa": "پول دادن برای کالا یا خدمات.",
      "en": "To give money for goods or services."
    },
    "conjugations": [
      "bezahlen",
      "bezahlt",
      "bezahlte",
      "hat bezahlt"
    ],
    "examples": {
      "fa": [
        "Kann ich mit Karte bezahlen?",
        "آیا می‌توانم با کارت پرداخت کنم؟"
      ],
      "en": [
        "Ich bezahle bar.",
        "I'll pay in cash."
      ]
    }
  },
  {
    "word": "der Urlaub",
    "translations": {
      "fa": "تعطیلات، مرخصی",
      "en": "vacation, holiday"
    },
    "explanation": {
      "fa": "دوره‌ای که از کار یا مدرسه آزاد هستید برای استراحت یا سفر.",
      "en": "A period when you are free from work or school to rest or travel."
    },
    "conjugations": null,
    "examples": {
      "fa": [
        "Ich fahre im Sommer in den Urlaub.",
        "من در تابستان به مرخصی می‌روم."
      ],
      "en": [
        "Wo machst du Urlaub?",
        "Where are you going on vacation?"
      ]
    }
  },
  {
    "word": "reisen",
    "translations": {
      "fa": "مسافرت کردن",
      "en": "to travel"
    },
    "explanation": {
      "fa": "رفتن از یک مکان به مکان دیگر، معمولاً به مکان‌های دور.",
      "en": "To go from one place to another, usually to distant places."
    },
    "conjugations": [
      "reisen",
      "reist",
      "reiste",
      "ist gereist"
    ],
    "examples": {
      "fa": [
        "Ich reise gern nach Italien.",
        "من دوست دارم به ایتالیا سفر کنم."
      ],
      "en": [
        "Wir reisen mit dem Zug.",
        "We're traveling by train."
      ]
    }
  },
  {
    "word": "der Zug",
    "translations": {
      "fa": "قطار",
      "en": "train"
    },
    "explanation": {
      "fa": "وسیله نقلیه ریلی برای حمل مسافر یا کالا.",
      "en": "A rail vehicle for transporting passengers or goods."
    },
    "conjugations": null,
    "examples": {
      "fa": [
        "Der Zug fährt um 10 Uhr ab.",
        "قطار ساعت ۱۰ حرکت می‌کند."
      ],
      "en": [
        "Ich nehme den Zug zur Arbeit.",
        "I take the train to work."
      ]
    }
  },
  {
    "word": "der Flughafen",
    "translations": {
      "fa": "فرودگاه",
      "en": "airport"
    },
    "explanation": {
      "fa": "مکانی که هواپیماها از آنجا پرواز می‌کنند و فرود می‌آیند.",
      "en": "A place where airplanes take off and land."
    },
    "conjugations": null,
    "examples": {
      "fa": [
        "Wir treffen uns am Flughafen.",
        "ما در فرودگاه همدیگر را ملاقات می‌کنیم."
      ],
      "en": [
        "Der Flughafen ist 20 Kilometer entfernt.",
        "The airport is 20 kilometers away."
      ]
    }
  },
  {
    "word": "das Gepäck",
    "translations": {
      "fa": "چمدان، بار",
      "en": "luggage, baggage"
    },
    "explanation": {
      "fa": "کیف‌ها و چمدان‌هایی که در سفر با خود می‌برید.",
      "en": "Bags and suitcases you take with you when traveling."
    },
    "conjugations": null,
    "examples": {
      "fa": [
        "Wo ist mein Gepäck?",
        "چمدان من کجاست؟"
      ],
      "en": [
        "Das Gepäck ist zu schwer.",
        "The luggage is too heavy."
      ]
    }
  },
  {
    "word": "ankommen",
    "translations": {
      "fa": "رسیدن",
      "en": "to arrive"
    },
    "explanation": {
      "fa": "به مقصد رسیدن.",
      "en": "To reach a destination."
    },
    "conjugations": [
      "ankommen",
      "kommt an",
      "kam an",
      "ist angekommen"
    ],
    "examples": {
      "fa": [
        "Wann kommst du an?",
        "کی می‌رسی؟"
      ],
      "en": [
        "Der Zug kommt um 15 Uhr an.",
        "The train arrives at 3 PM."
      ]
    }
  },
  {
    "word": "abfahren",
    "translations": {
      "fa": "حرکت کردن",
      "en": "to depart, to leave"
    },
    "explanation": {
      "fa": "شروع سفر کردن؛ ترک کردن مکانی.",
      "en": "To start a journey; to leave a place."
    },
    "conjugations": [
      "abfahren",
      "fährt ab",
      "fuhr ab",
      "ist abgefahren"
    ],
    "examples": {
      "fa": [
        "Der Bus fährt in 5 Minuten ab.",
        "اتوبوس ۵ دقیقه دیگر حرکت می‌کند."
      ],
      "en": [
        "Wann fährst du ab?",
        "When are you leaving?"
      ]
    }
  },
  {
    "word": "die Gesundheit",
    "translations": {
      "fa": "سلامتی",
      "en": "health"
    },
    "explanation": {
      "fa": "وضعیت بدنی و ذهنی؛ حالت خوب بدن.",
      "en": "The state of physical and mental well-being."
    },
    "conjugations": null,
    "examples": {
      "fa": [
        "Gesundheit ist das Wichtigste.",
        "سلامتی مهم‌ترین چیز است."
      ],
      "en": [
        "Ich achte auf meine Gesundheit.",
        "I take care of my health."
      ]
    }
  },
  {
    "word": "der Arzt",
    "translations": {
      "fa": "دکتر، پزشک",
      "en": "doctor, physician"
    },
    "explanation": {
      "fa": "شخصی که به بیماران کمک می‌کند و آنها را درمان می‌کند.",
      "en": "A person who helps and treats sick people."
    },
    "conjugations": null,
    "examples": {
      "fa": [
        "Ich habe einen Termin beim Arzt.",
        "من قرار ملاقات با دکتر دارم."
      ],
      "en": [
        "Der Arzt hat mir Medikamente verschrieben.",
        "The doctor prescribed me medication."
      ]
    }
  },
  {
    "word": "die Apotheke",
    "translations": {
      "fa": "داروخانه",
      "en": "pharmacy"
    },
    "explanation": {
      "fa": "مکانی که دارو و محصولات بهداشتی می‌فروشد.",
      "en": "A place that sells medicines and health products."
    },
    "conjugations": null,
    "examples": {
      "fa": [
        "Ich gehe zur Apotheke.",
        "من به داروخانه می‌روم."
      ],
      "en": [
        "Die Apotheke ist heute geschlossen.",
        "The pharmacy is closed today."
      ]
    }
  },
  {
    "word": "das Medikament",
    "translations": {
      "fa": "دارو",
      "en": "medicine, medication"
    },
    "explanation": {
      "fa": "مادهٔ شیمیایی برای درمان بیماری.",
      "en": "A chemical substance used to treat illness."
    },
    "conjugations": null,
    "examples": {
      "fa": [
        "Ich muss dieses Medikament nehmen.",
        "من باید این دارو را مصرف کنم."
      ],
      "en": [
        "Das Medikament hilft gegen Kopfschmerzen.",
        "The medicine helps with headaches."
      ]
    }
  },
  {
    "word": "der Termin",
    "translations": {
      "fa": "قرار ملاقات",
      "en": "appointment"
    },
    "explanation": {
      "fa": "زمان و مکان تعیین‌شده برای ملاقات.",
      "en": "A scheduled time and place for a meeting."
    },
    "conjugations": null,
    "examples": {
      "fa": [
        "Ich habe morgen einen Termin.",
        "من فردا یک قرار ملاقات دارم."
      ],
      "en": [
        "Können wir einen Termin vereinbaren?",
        "Can we make an appointment?"
      ]
    }
  },
  {
    "word": "die Schule",
    "translations": {
      "fa": "مدرسه",
      "en": "school"
    },
    "explanation": {
      "fa": "مکانی برای آموزش و یادگیری.",
      "en": "A place for teaching and learning."
    },
    "conjugations": null,
    "examples": {
      "fa": [
        "Die Kinder gehen zur Schule.",
        "بچه‌ها به مدرسه می‌روند."
      ],
      "en": [
        "Die Schule beginnt um 8 Uhr.",
        "School starts at 8 o'clock."
      ]
    }
  },
  {
    "word": "der Unterricht",
    "translations": {
      "fa": "درس، کلاس",
      "en": "lesson, class"
    },
    "explanation": {
      "fa": "دورهٔ آموزشی؛ کلاس درسی.",
      "en": "A teaching session; a class."
    },
    "conjugations": null,
    "examples": {
      "fa": [
        "Der Unterricht dauert 90 Minuten.",
        "کلاس ۹۰ دقیقه طول می‌کشد."
      ],
      "en": [
        "Ich habe heute drei Unterrichtsstunden.",
        "I have three lessons today."
      ]
    }
  },
  {
    "word": "die Prüfung",
    "translations": {
      "fa": "امتحان",
      "en": "exam, test"
    },
    "explanation": {
      "fa": "آزمونی برای سنجش دانش یا مهارت.",
      "en": "A test to measure knowledge or skill."
    },
    "conjugations": null,
    "examples": {
      "fa": [
        "Ich habe nächste Woche eine Prüfung.",
        "من هفتهٔ آینده یک امتحان دارم."
      ],
      "en": [
        "Die Prüfung war sehr schwierig.",
        "The exam was very difficult."
      ]
    }
  },
  {
    "word": "bestehen",
    "translations": {
      "fa": "قبول شدن",
      "en": "to pass (an exam)"
    },
    "explanation": {
      "fa": "در امتحان موفق شدن.",
      "en": "To succeed in an exam."
    },
    "conjugations": [
      "bestehen",
      "besteht",
      "bestand",
      "hat bestanden"
    ],
    "examples": {
      "fa": [
        "Ich habe die Prüfung bestanden!",
        "من در امتحان قبول شدم!"
      ],
      "en": [
        "Er hat alle Prüfungen bestanden.",
        "He passed all the exams."
      ]
    }
  },
  {
    "word": "das Restaurant",
    "translations": {
      "fa": "رستوران",
      "en": "restaurant"
    },
    "explanation": {
      "fa": "مکانی برای خوردن غذا که غذا را برای شما آماده می‌کنند.",
      "en": "A place where food is prepared and served to customers."
    },
    "conjugations": null,
    "examples": {
      "fa": [
        "Lass uns in ein Restaurant gehen.",
        "بیا به رستوران برویم."
      ],
      "en": [
        "Das Restaurant ist sehr beliebt.",
        "The restaurant is very popular."
      ]
    }
  },
  {
    "word": "bestellen",
    "translations": {
      "fa": "سفارش دادن",
      "en": "to order"
    },
    "explanation": {
      "fa": "درخواست غذا یا کالا کردن.",
      "en": "To request food or goods."
    },
    "conjugations": [
      "bestellen",
      "bestellt",
      "bestellte",
      "hat bestellt"
    ],
    "examples": {
      "fa": [
        "Was möchtest du bestellen?",
        "چه چیزی می‌خواهی سفارش بدهی؟"
      ],
      "en": [
        "Ich bestelle einen Kaffee.",
        "I'm ordering a coffee."
      ]
    }
  },
  {
    "word": "die Speisekarte",
    "translations": {
      "fa": "منو، لیست غذا",
      "en": "menu"
    },
    "explanation": {
      "fa": "لیست غذاها و نوشیدنی‌ها در رستوران.",
      "en": "A list of food and drinks in a restaurant."
    },
    "conjugations": null,
    "examples": {
      "fa": [
        "Kann ich bitte die Speisekarte haben?",
        "لطفاً منو را می‌توانم ببینم؟"
      ],
      "en": [
        "Die Speisekarte ist sehr umfangreich.",
        "The menu is very extensive."
      ]
    }
  },
  {
    "word": "schmecken",
    "translations": {
      "fa": "مزه داشتن، خوشمزه بودن",
      "en": "to taste"
    },
    "explanation": {
      "fa": "طعم خاصی داشتن؛ خوشایند بودن.",
      "en": "To have a particular flavor; to be pleasant."
    },
    "conjugations": [
      "schmecken",
      "schmeckt",
      "schmeckte",
      "hat geschmeckt"
    ],
    "examples": {
      "fa": [
        "Das Essen schmeckt sehr gut.",
        "غذا خیلی خوشمزه است."
      ],
      "en": [
        "Schmeckt dir der Kuchen?",
        "Do you like the cake?"
      ]
    }
  },
  {
    "word": "das Wetter",
    "translations": {
      "fa": "آب و هوا",
      "en": "weather"
    },
    "explanation": {
      "fa": "شرایط جوی در یک زمان و مکان خاص.",
      "en": "Atmospheric conditions at a specific time and place."
    },
    "conjugations": null,
    "examples": {
      "fa": [
        "Wie ist das Wetter heute?",
        "امروز هوا چطور است؟"
      ],
      "en": [
        "Das Wetter ist schön.",
        "The weather is nice."
      ]
    }
  },
  {
    "word": "der Regen",
    "translations": {
      "fa": "باران",
      "en": "rain"
    },
    "explanation": {
      "fa": "قطرات آب که از آسمان می‌بارد.",
      "en": "Water droplets falling from the sky."
    },
    "conjugations": null,
    "examples": {
      "fa": [
        "Es gibt heute Regen.",
        "امروز باران می‌بارد."
      ],
      "en": [
        "Der Regen hat aufgehört.",
        "The rain has stopped."
      ]
    }
  },
  {
    "word": "der Schnee",
    "translations": {
      "fa": "برف",
      "en": "snow"
    },
    "explanation": {
      "fa": "بارش سفید و سرد که از آسمان می‌بارد.",
      "en": "White, cold precipitation falling from the sky."
    },
    "conjugations": null,
    "examples": {
      "fa": [
        "Im Winter gibt es viel Schnee.",
        "در زمستان برف زیادی می‌بارد."
      ],
      "en": [
        "Die Kinder spielen im Schnee.",
        "The children are playing in the snow."
      ]
    }
  },
  {
    "word": "die Sonne",
    "translations": {
      "fa": "خورشید",
      "en": "sun"
    },
    "explanation": {
      "fa": "ستاره‌ای که به زمین نور و گرما می‌دهد.",
      "en": "The star that gives Earth light and warmth."
    },
    "conjugations": null,
    "examples": {
      "fa": [
        "Die Sonne scheint heute.",
        "امروز خورشید می‌تابد."
      ],
      "en": [
        "Ich liebe die Sonne.",
        "I love the sun."
      ]
    }
  },
  {
    "word": "wichtig",
    "translations": {
      "fa": "مهم",
      "en": "important"
    },
    "explanation": {
      "fa": "دارای اهمیت و ارزش زیاد.",
      "en": "Having great significance and value."
    },
    "conjugations": null,
    "examples": {
      "fa": [
        "Das ist sehr wichtig.",
        "این خیلی مهم است."
      ],
      "en": [
        "Gesundheit ist wichtig.",
        "Health is important."
      ]
    }
  },
  {
    "word": "schwierig",
    "translations": {
      "fa": "سخت، مشکل",
      "en": "difficult, hard"
    },
    "explanation": {
      "fa": "نیازمند تلاش زیاد؛ دشوار.",
      "en": "Requiring much effort; challenging."
    },
    "conjugations": null,
    "examples": {
      "fa": [
        "Die Aufgabe ist sehr schwierig.",
        "این تکلیف خیلی سخت است."
      ],
      "en": [
        "Deutsch ist schwierig.",
        "German is difficult."
      ]
    }
  },
  {
    "word": "einfach",
    "translations": {
      "fa": "آسان، ساده",
      "en": "easy, simple"
    },
    "explanation": {
      "fa": "بدون پیچیدگی؛ آسان برای انجام.",
      "en": "Without complexity; easy to do."
    },
    "conjugations": null,
    "examples": {
      "fa": [
        "Das ist ganz einfach.",
        "این خیلی ساده است."
      ],
      "en": [
        "Die Übung ist einfach.",
        "The exercise is easy."
      ]
    }
  },
  {
    "word": "teuer",
    "translations": {
      "fa": "گران",
      "en": "expensive"
    },
    "explanation": {
      "fa": "قیمت زیاد داشتن.",
      "en": "Having a high price."
    },
    "conjugations": null,
    "examples": {
      "fa": [
        "Das Auto ist sehr teuer.",
        "این ماشین خیلی گران است."
      ],
      "en": [
        "Diese Schuhe sind zu teuer.",
        "These shoes are too expensive."
      ]
    }
  },
  {
    "word": "billig",
    "translations": {
      "fa": "ارزان",
      "en": "cheap, inexpensive"
    },
    "explanation": {
      "fa": "قیمت کم داشتن.",
      "en": "Having a low price."
    },
    "conjugations": null,
    "examples": {
      "fa": [
        "Das Buch war sehr billig.",
        "کتاب خیلی ارزان بود."
      ],
      "en": [
        "Wo kann ich billig einkaufen?",
        "Where can I shop cheaply?"
      ]
    }
  },
  {
    "word": "müde",
    "translations": {
      "fa": "خسته",
      "en": "tired"
    },
    "explanation": {
      "fa": "احساس کمبود انرژی؛ نیاز به استراحت.",
      "en": "Feeling a lack of energy; needing rest."
    },
    "conjugations": null,
    "examples": {
      "fa": [
        "Ich bin sehr müde.",
        "من خیلی خسته‌ام."
      ],
      "en": [
        "Nach der Arbeit bin ich immer müde.",
        "After work I'm always tired."
      ]
    }
  },
  {
    "word": "wach",
    "translations": {
      "fa": "بیدار",
      "en": "awake"
    },
    "explanation": {
      "fa": "در حالت بیداری؛ نه خواب.",
      "en": "In a state of wakefulness; not asleep."
    },
    "conjugations": null,
    "examples": {
      "fa": [
        "Bist du noch wach?",
        "هنوز بیداری؟"
      ],
      "en": [
        "Ich bin schon lange wach.",
        "I've been awake for a long time."
      ]
    }
  },
  {
    "word": "schlafen",
    "translations": {
      "fa": "خوابیدن",
      "en": "to sleep"
    },
    "explanation": {
      "fa": "حالت استراحت طبیعی بدن با بستن چشم‌ها.",
      "en": "Natural rest state of the body with closed eyes."
    },
    "conjugations": [
      "schlafen",
      "schläft",
      "schlief",
      "hat geschlafen"
    ],
    "examples": {
      "fa": [
        "Ich schlafe 8 Stunden pro Nacht.",
        "من ۸ ساعت در شب می‌خوابم."
      ],
      "en": [
        "Das Baby schläft.",
        "The baby is sleeping."
      ]
    }
  },
  {
    "word": "aufwachen",
    "translations": {
      "fa": "بیدار شدن",
      "en": "to wake up"
    },
    "explanation": {
      "fa": "از خواب برخاستن.",
      "en": "To stop sleeping."
    },
    "conjugations": [
      "aufwachen",
      "wacht auf",
      "wachte auf",
      "ist aufgewacht"
    ],
    "examples": {
      "fa": [
        "Ich wache um 7 Uhr auf.",
        "من ساعت ۷ بیدار می‌شوم."
      ],
      "en": [
        "Wann bist du heute aufgewacht?",
        "When did you wake up today?"
      ]
    }
  },
  {
    "word": "die Zeit",
    "translations": {
      "fa": "زمان",
      "en": "time"
    },
    "explanation": {
      "fa": "دوره یا لحظهٔ خاص؛ ساعت.",
      "en": "A particular period or moment; the hour."
    },
    "conjugations": null,
    "examples": {
      "fa": [
        "Ich habe keine Zeit.",
        "من وقت ندارم."
      ],
      "en": [
        "Wie viel Zeit haben wir?",
        "How much time do we have?"
      ]
    }
  },
  {
    "word": "früh",
    "translations": {
      "fa": "زود، اوایل",
      "en": "early"
    },
    "explanation": {
      "fa": "در آغاز روز یا قبل از زمان معمول.",
      "en": "At the beginning of the day or before the usual time."
    },
    "conjugations": null,
    "examples": {
      "fa": [
        "Ich stehe früh auf.",
        "من زود بیدار می‌شوم."
      ],
      "en": [
        "Es ist noch zu früh.",
        "It's still too early."
      ]
    }
  },
  {
    "word": "spät",
    "translations": {
      "fa": "دیر",
      "en": "late"
    },
    "explanation": {
      "fa": "بعد از زمان معمول یا انتظار.",
      "en": "After the usual or expected time."
    },
    "conjugations": null,
    "examples": {
      "fa": [
        "Es ist schon spät.",
        "دیگر دیر شده است."
      ],
      "en": [
        "Ich komme heute spät nach Hause.",
        "I'm coming home late today."
      ]
    }
  },
  {
    "word": "pünktlich",
    "translations": {
      "fa": "سر وقت",
      "en": "on time, punctual"
    },
    "explanation": {
      "fa": "در زمان دقیق و مشخص‌شده.",
      "en": "At the exact scheduled time."
    },
    "conjugations": null,
    "examples": {
      "fa": [
        "Bitte sei pünktlich!",
        "لطفاً سر وقت باش!"
      ],
      "en": [
        "Der Zug ist immer pünktlich.",
        "The train is always on time."
      ]
    }
  },
  {
    "word": "vergessen",
    "translations": {
      "fa": "فراموش کردن",
      "en": "to forget"
    },
    "explanation": {
      "fa": "به یاد نیاوردن چیزی.",
      "en": "To fail to remember something."
    },
    "conjugations": [
      "vergessen",
      "vergisst",
      "vergaß",
      "hat vergessen"
    ],
    "examples": {
      "fa": [
        "Ich habe meinen Schlüssel vergessen.",
        "من کلیدم را فراموش کرده‌ام."
      ],
      "en": [
        "Vergiss nicht, mich anzurufen!",
        "Don't forget to call me!"
      ]
    }
  },
  {
    "word": "erinnern",
    "translations": {
      "fa": "یادآوری کردن، به یاد آوردن",
      "en": "to remember, to remind"
    },
    "explanation": {
      "fa": "چیزی را به خاطر آوردن یا به کسی یادآوری کردن.",
      "en": "To recall something or remind someone."
    },
    "conjugations": [
      "erinnern",
      "erinnert",
      "erinnerte",
      "hat erinnert"
    ],
    "examples": {
      "fa": [
        "Ich erinnere mich an dich.",
        "من تو را به یاد می‌آورم."
      ],
      "en": [
        "Kannst du mich daran erinnern?",
        "Can you remind me of that?"
      ]
    }
  },
  {
    "word": "der Computer",
    "translations": {
      "fa": "رایانه، کامپیوتر",
      "en": "computer"
    },
    "explanation": {
      "fa": "دستگاه الکترونیکی برای پردازش اطلاعات.",
      "en": "Electronic device for processing information."
    },
    "conjugations": null,
    "examples": {
      "fa": [
        "Ich arbeite am Computer.",
        "من با کامپیوتر کار می‌کنم."
      ],
      "en": [
        "Mein Computer ist kaputt.",
        "My computer is broken."
      ]
    }
  },
  {
    "word": "das Handy",
    "translations": {
      "fa": "موبایل، تلفن همراه",
      "en": "mobile phone, cell phone"
    },
    "explanation": {
      "fa": "تلفن قابل حمل برای تماس و ارتباطات.",
      "en": "Portable phone for calls and communication."
    },
    "conjugations": null,
    "examples": {
      "fa": [
        "Wo ist mein Handy?",
        "موبایل من کجاست؟"
      ],
      "en": [
        "Das Handy klingelt.",
        "The phone is ringing."
      ]
    }
  },
  {
    "word": "die E-Mail",
    "translations": {
      "fa": "ایمیل",
      "en": "email"
    },
    "explanation": {
      "fa": "پیام الکترونیکی ارسال‌شده از طریق اینترنت.",
      "en": "Electronic message sent via the internet."
    },
    "conjugations": null,
    "examples": {
      "fa": [
        "Ich schicke dir eine E-Mail.",
        "من برایت یک ایمیل می‌فرستم."
      ],
      "en": [
        "Hast du meine E-Mail bekommen?",
        "Did you receive my email?"
      ]
    }
  },
  {
    "word": "das Internet",
    "translations": {
      "fa": "اینترنت",
      "en": "internet"
    },
    "explanation": {
      "fa": "شبکهٔ جهانی اطلاعات و ارتباطات.",
      "en": "Global network of information and communication."
    },
    "conjugations": null,
    "examples": {
      "fa": [
        "Ich surfe im Internet.",
        "من در اینترنت گشت می‌زنم."
      ],
      "en": [
        "Das Internet funktioniert nicht.",
        "The internet isn't working."
      ]
    }
  },
  {
    "word": "suchen",
    "translations": {
      "fa": "جستجو کردن",
      "en": "to search, to look for"
    },
    "explanation": {
      "fa": "تلاش برای یافتن چیزی.",
      "en": "To try to find something."
    },
    "conjugations": [
      "suchen",
      "sucht",
      "suchte",
      "hat gesucht"
    ],
    "examples": {
      "fa": [
        "Ich suche meine Brille.",
        "من دنبال عینکم می‌گردم."
      ],
      "en": [
        "Was suchst du?",
        "What are you looking for?"
      ]
    }
  },
  {
    "word": "finden",
    "translations": {
      "fa": "پیدا کردن",
      "en": "to find"
    },
    "explanation": {
      "fa": "چیزی را که جستجو می‌کنید کشف کردن.",
      "en": "To discover something you're looking for."
    },
    "conjugations": [
      "finden",
      "findet",
      "fand",
      "hat gefunden"
    ],
    "examples": {
      "fa": [
        "Ich habe meinen Schlüssel gefunden.",
        "من کلیدم را پیدا کردم."
      ],
      "en": [
        "Wo kann ich das finden?",
        "Where can I find that?"
      ]
    }
  },
  {
    "word": "verlieren",
    "translations": {
      "fa": "گم کردن",
      "en": "to lose"
    },
    "explanation": {
      "fa": "چیزی را نداشته باشید که قبلاً داشتید.",
      "en": "To no longer have something you previously had."
    },
    "conjugations": [
      "verlieren",
      "verliert",
      "verlor",
      "hat verloren"
    ],
    "examples": {
      "fa": [
        "Ich habe meine Tasche verloren.",
        "من کیفم را گم کرده‌ام."
      ],
      "en": [
        "Hast du etwas verloren?",
        "Did you lose something?"
      ]
    }
  },
  {
    "word": "gewinnen",
    "translations": {
      "fa": "برنده شدن",
      "en": "to win"
    },
    "explanation": {
      "fa": "در مسابقه یا بازی موفق شدن.",
      "en": "To succeed in a competition or game."
    },
    "conjugations": [
      "gewinnen",
      "gewinnt",
      "gewann",
      "hat gewonnen"
    ],
    "examples": {
      "fa": [
        "Unser Team hat gewonnen!",
        "تیم ما برنده شد!"
      ],
      "en": [
        "Wer hat das Spiel gewonnen?",
        "Who won the game?"
      ]
    }
  },
  {
    "word": "das Spiel",
    "translations": {
      "fa": "بازی",
      "en": "game"
    },
    "explanation": {
      "fa": "فعالیت سرگرم‌کننده با قوانین.",
      "en": "An entertaining activity with rules."
    },
    "conjugations": null,
    "examples": {
      "fa": [
        "Lass uns ein Spiel spielen.",
        "بیا یک بازی کنیم."
      ],
      "en": [
        "Das Spiel beginnt um 18 Uhr.",
        "The game starts at 6 PM."
      ]
    }
  },
  {
    "word": "der Sport",
    "translations": {
      "fa": "ورزش",
      "en": "sport"
    },
    "explanation": {
      "fa": "فعالیت بدنی برای تفریح یا مسابقه.",
      "en": "Physical activity for recreation or competition."
    },
    "conjugations": null,
    "examples": {
      "fa": [
        "Ich treibe gern Sport.",
        "من دوست دارم ورزش کنم."
      ],
      "en": [
        "Welchen Sport machst du?",
        "What sport do you do?"
      ]
    }
  },
  {
    "word": "laufen",
    "translations": {
      "fa": "دویدن",
      "en": "to run"
    },
    "explanation": {
      "fa": "سریع حرکت کردن با پاها.",
      "en": "To move quickly with the legs."
    },
    "conjugations": [
      "laufen",
      "läuft",
      "lief",
      "ist gelaufen"
    ],
    "examples": {
      "fa": [
        "Ich laufe jeden Morgen.",
        "من هر صبح می‌دوم."
      ],
      "en": [
        "Die Kinder laufen im Park.",
        "The children are running in the park."
      ]
    }
  },
  {
    "word": "schwimmen",
    "translations": {
      "fa": "شنا کردن",
      "en": "to swim"
    },
    "explanation": {
      "fa": "در آب حرکت کردن.",
      "en": "To move through water."
    },
    "conjugations": [
      "schwimmen",
      "schwimmt",
      "schwamm",
      "ist geschwommen"
    ],
    "examples": {
      "fa": [
        "Ich gehe schwimmen.",
        "من می‌روم شنا."
      ],
      "en": [
        "Kannst du schwimmen?",
        "Can you swim?"
      ]
    }
  },
  {
    "word": "der Freund",
    "translations": {
      "fa": "دوست",
      "en": "friend"
    },
    "explanation": {
      "fa": "شخصی که دوستش دارید و با او وقت می‌گذرانید.",
      "en": "A person you like and spend time with."
    },
    "conjugations": null,
    "examples": {
      "fa": [
        "Das ist mein bester Freund.",
        "این بهترین دوست من است."
      ],
      "en": [
        "Ich treffe meine Freunde.",
        "I'm meeting my friends."
      ]
    }
  },
  {
    "word": "die Familie",
    "translations": {
      "fa": "خانواده",
      "en": "family"
    },
    "explanation": {
      "fa": "گروهی از افراد که با هم زندگی می‌کنند یا خویشاوند هستند.",
      "en": "A group of people living together or related by blood."
    },
    "conjugations": null,
    "examples": {
      "fa": [
        "Ich besuche meine Familie.",
        "من به دیدن خانواده‌ام می‌روم."
      ],
      "en": [
        "Meine Familie ist sehr groß.",
        "My family is very large."
      ]
    }
  },
  {
    "word": "die Eltern",
    "translations": {
      "fa": "والدین",
      "en": "parents"
    },
    "explanation": {
      "fa": "پدر و مادر.",
      "en": "Mother and father."
    },
    "conjugations": null,
    "examples": {
      "fa": [
        "Meine Eltern wohnen in Berlin.",
        "والدین من در برلین زندگی می‌کنند."
      ],
      "en": [
        "Ich rufe meine Eltern an.",
        "I'm calling my parents."
      ]
    }
  },
  {
    "word": "das Kind",
    "translations": {
      "fa": "بچه، کودک",
      "en": "child"
    },
    "explanation": {
      "fa": "فرد جوان؛ پسر یا دختر.",
      "en": "A young person; a boy or girl."
    },
    "conjugations": null,
    "examples": {
      "fa": [
        "Ich habe zwei Kinder.",
        "من دو بچه دارم."
      ],
      "en": [
        "Die Kinder spielen draußen.",
        "The children are playing outside."
      ]
    }
  },
  {
    "word": "helfen",
    "translations": {
      "fa": "کمک کردن",
      "en": "to help"
    },
    "explanation": {
      "fa": "به کسی در انجام کاری یاری رساندن.",
      "en": "To assist someone in doing something."
    },
    "conjugations": [
      "helfen",
      "hilft",
      "half",
      "hat geholfen"
    ],
    "examples": {
      "fa": [
        "Kann ich dir helfen?",
        "می‌توانم کمکت کنم؟"
      ],
      "en": [
        "Er hilft mir bei den Hausaufgaben.",
        "He helps me with homework."
      ]
    }
  },
  {
    "word": "danken",
    "translations": {
      "fa": "تشکر کردن",
      "en": "to thank"
    },
    "explanation": {
      "fa": "ابراز قدردانی کردن.",
      "en": "To express gratitude."
    },
    "conjugations": [
      "danken",
      "dankt",
      "dankte",
      "hat gedankt"
    ],
    "examples": {
      "fa": [
        "Ich danke dir!",
        "از تو تشکر می‌کنم!"
      ],
      "en": [
        "Sie dankt ihm für die Hilfe.",
        "She thanks him for the help."
      ]
    }
  },
  {
    "word": "bitte",
    "translations": {
      "fa": "لطفاً، خواهش می‌کنم",
      "en": "please, you're welcome"
    },
    "explanation": {
      "fa": "کلمه‌ای برای مودبانه درخواست کردن یا پاسخ به تشکر.",
      "en": "A word for politely requesting or responding to thanks."
    },
    "conjugations": null,
    "examples": {
      "fa": [
        "Bitte schön!",
        "خواهش می‌کنم!"
      ],
      "en": [
        "Ein Kaffee, bitte.",
        "A coffee, please."
      ]
    }
  },
  {
    "word": "entschuldigen",
    "translations": {
      "fa": "عذرخواهی کردن",
      "en": "to apologize, to excuse"
    },
    "explanation": {
      "fa": "ابراز پشیمانی کردن؛ بخشش خواستن.",
      "en": "To express regret; to ask for forgiveness."
    },
    "conjugations": [
      "entschuldigen",
      "entschuldigt",
      "entschuldigte",
      "hat entschuldigt"
    ],
    "examples": {
      "fa": [
        "Entschuldigung!",
        "ببخشید!"
      ],
      "en": [
        "Ich entschuldige mich für den Fehler.",
        "I apologize for the mistake."
      ]
    }
  },
  {
    "word": "freuen",
    "translations": {
      "fa": "خوشحال بودن",
      "en": "to be happy, to look forward to"
    },
    "explanation": {
      "fa": "احساس شادی کردن.",
      "en": "To feel joy."
    },
    "conjugations": [
      "freuen",
      "freut",
      "freute",
      "hat gefreut"
    ],
    "examples": {
      "fa": [
        "Ich freue mich auf den Urlaub.",
        "من منتظر تعطیلات هستم."
      ],
      "en": [
        "Das freut mich!",
        "That makes me happy!"
      ]
    }
  },
  {
    "word": "glücklich",
    "translations": {
      "fa": "خوشبخت، شاد",
      "en": "happy"
    },
    "explanation": {
      "fa": "احساس شادی و رضایت.",
      "en": "Feeling joy and contentment."
    },
    "conjugations": null,
    "examples": {
      "fa": [
        "Ich bin sehr glücklich.",
        "من خیلی خوشحالم."
      ],
      "en": [
        "Sie ist glücklich verheiratet.",
        "She is happily married."
      ]
    }
  },
  {
    "word": "traurig",
    "translations": {
      "fa": "غمگین",
      "en": "sad"
    },
    "explanation": {
      "fa": "احساس ناراحتی و اندوه.",
      "en": "Feeling unhappy and sorrowful."
    },
    "conjugations": null,
    "examples": {
      "fa": [
        "Warum bist du traurig?",
        "چرا غمگینی؟"
      ],
      "en": [
        "Das ist eine traurige Geschichte.",
        "That's a sad story."
      ]
    }
  },
  {
    "word": "wütend",
    "translations": {
      "fa": "عصبانی",
      "en": "angry"
    },
    "explanation": {
      "fa": "احساس خشم و ناراحتی شدید.",
      "en": "Feeling intense displeasure and rage."
    },
    "conjugations": null,
    "examples": {
      "fa": [
        "Er ist wütend auf mich.",
        "او از من عصبانی است."
      ],
      "en": [
        "Sei nicht wütend!",
        "Don't be angry!"
      ]
    }
  },
  {
    "word": "die Angst",
    "translations": {
      "fa": "ترس",
      "en": "fear, anxiety"
    },
    "explanation": {
      "fa": "احساس ترس یا نگرانی.",
      "en": "Feeling of fear or worry."
    },
    "conjugations": null,
    "examples": {
      "fa": [
        "Ich habe Angst vor Spinnen.",
        "من از عنکبوت می‌ترسم."
      ],
      "en": [
        "Keine Angst!",
        "Don't be afraid!"
      ]
    }
  },
  {
    "word": "hoffen",
    "translations": {
      "fa": "امیدوار بودن",
      "en": "to hope"
    },
    "explanation": {
      "fa": "آرزو کردن که چیزی اتفاق بیفتد.",
      "en": "To wish for something to happen."
    },
    "conjugations": [
      "hoffen",
      "hofft",
      "hoffte",
      "hat gehofft"
    ],
    "examples": {
      "fa": [
        "Ich hoffe, dass alles gut geht.",
        "امیدوارم همه چیز خوب پیش برود."
      ],
      "en": [
        "Wir hoffen auf besseres Wetter.",
        "We hope for better weather."
      ]
    }
  },
  {
    "word": "glauben",
    "translations": {
      "fa": "باور کردن",
      "en": "to believe"
    },
    "explanation": {
      "fa": "چیزی را واقعیت یا حقیقت دانستن.",
      "en": "To accept something as true or real."
    },
    "conjugations": [
      "glauben",
      "glaubt",
      "glaubte",
      "hat geglaubt"
    ],
    "examples": {
      "fa": [
        "Ich glaube dir.",
        "من تو را باور می‌کنم."
      ],
      "en": [
        "Glaubst du das wirklich?",
        "Do you really believe that?"
      ]
    }
  },
  {
    "word": "wissen",
    "translations": {
      "fa": "دانستن",
      "en": "to know"
    },
    "explanation": {
      "fa": "اطلاعات یا دانش داشتن درباره چیزی.",
      "en": "To have information or knowledge about something."
    },
    "conjugations": [
      "wissen",
      "weiß",
      "wusste",
      "hat gewusst"
    ],
    "examples": {
      "fa": [
        "Ich weiß es nicht.",
        "من نمی‌دانم."
      ],
      "en": [
        "Weißt du, wo er wohnt?",
        "Do you know where he lives?"
      ]
    }
  },
  {
    "word": "kennen",
    "translations": {
      "fa": "شناختن",
      "en": "to know (a person or place)"
    },
    "explanation": {
      "fa": "با شخص یا مکانی آشنا بودن.",
      "en": "To be familiar with a person or place."
    },
    "conjugations": [
      "kennen",
      "kennt",
      "kannte",
      "hat gekannt"
    ],
    "examples": {
      "fa": [
        "Ich kenne ihn gut.",
        "من او را خوب می‌شناسم."
      ],
      "en": [
        "Kennst du diese Stadt?",
        "Do you know this city?"
      ]
    }
  },
  {
    "word": "treffen",
    "translations": {
      "fa": "ملاقات کردن",
      "en": "to meet"
    },
    "explanation": {
      "fa": "با کسی دیدار کردن.",
      "en": "To see and talk to someone."
    },
    "conjugations": [
      "treffen",
      "trifft",
      "traf",
      "hat getroffen"
    ],
    "examples": {
      "fa": [
        "Wann treffen wir uns?",
        "کی همدیگر را ملاقات می‌کنیم؟"
      ],
      "en": [
        "Ich treffe meine Freunde heute Abend.",
        "I'm meeting my friends this evening."
      ]
    }
  },
  {
    "word": "besuchen",
    "translations": {
      "fa": "بازدید کردن",
      "en": "to visit"
    },
    "explanation": {
      "fa": "رفتن به دیدن کسی یا مکانی.",
      "en": "To go to see someone or a place."
    },
    "conjugations": [
      "besuchen",
      "besucht",
      "besuchte",
      "hat besucht"
    ],
    "examples": {
      "fa": [
        "Ich besuche meine Großeltern.",
        "من به دیدن پدربزرگ و مادربزرگم می‌روم."
      ],
      "en": [
        "Hast du das Museum besucht?",
        "Did you visit the museum?"
      ]
    }
  },
  {
    "word": "einladen",
    "translations": {
      "fa": "دعوت کردن",
      "en": "to invite"
    },
    "explanation": {
      "fa": "از کسی خواستن که به مهمانی یا رویداد بیاید.",
      "en": "To ask someone to come to a party or event."
    },
    "conjugations": [
      "einladen",
      "lädt ein",
      "lud ein",
      "hat eingeladen"
    ],
    "examples": {
      "fa": [
        "Ich lade dich zu meiner Party ein.",
        "من تو را به مهمانی‌ام دعوت می‌کنم."
      ],
      "en": [
        "Sie hat uns zum Abendessen eingeladen.",
        "She invited us to dinner."
      ]
    }
  },
  {
    "word": "die Party",
    "translations": {
      "fa": "مهمانی",
      "en": "party"
    },
    "explanation": {
      "fa": "گردهمایی اجتماعی برای جشن.",
      "en": "A social gathering for celebration."
    },
    "conjugations": null,
    "examples": {
      "fa": [
        "Kommst du zur Party?",
        "به مهمانی می‌آیی؟"
      ],
      "en": [
        "Die Party war toll!",
        "The party was great!"
      ]
    }
  },
  {
    "word": "feiern",
    "translations": {
      "fa": "جشن گرفتن",
      "en": "to celebrate"
    },
    "explanation": {
      "fa": "مراسمی برای یک مناسبت خاص برگزار کردن.",
      "en": "To hold a ceremony for a special occasion."
    },
    "conjugations": [
      "feiern",
      "feiert",
      "feierte",
      "hat gefeiert"
    ],
    "examples": {
      "fa": [
        "Wir feiern heute meinen Geburtstag.",
        "ما امروز تولدم را جشن می‌گیریم."
      ],
      "en": [
        "Wie feierst du Weihnachten?",
        "How do you celebrate Christmas?"
      ]
    }
  },
  {
    "word": "der Geburtstag",
    "translations": {
      "fa": "تولد",
      "en": "birthday"
    },
    "explanation": {
      "fa": "روز سالگرد تولد شخص.",
      "en": "The anniversary of the day someone was born."
    },
    "conjugations": null,
    "examples": {
      "fa": [
        "Herzlichen Glückwunsch zum Geburtstag!",
        "تولدت مبارک!"
      ],
      "en": [
        "Mein Geburtstag ist im Juli.",
        "My birthday is in July."
      ]
    }
  },
  {
    "word": "das Geschenk",
    "translations": {
      "fa": "هدیه",
      "en": "gift, present"
    },
    "explanation": {
      "fa": "چیزی که به کسی می‌دهید.",
      "en": "Something you give to someone."
    },
    "conjugations": null,
    "examples": {
      "fa": [
        "Das ist ein tolles Geschenk!",
        "این یک هدیهٔ عالی است!"
      ],
      "en": [
        "Ich kaufe ein Geschenk für meine Mutter.",
        "I'm buying a gift for my mother."
      ]
    }
  },
  {
    "word": "schenken",
    "translations": {
      "fa": "هدیه دادن",
      "en": "to give (as a gift)"
    },
    "explanation": {
      "fa": "چیزی را به کسی به‌عنوان هدیه دادن.",
      "en": "To give something to someone as a present."
    },
    "conjugations": [
      "schenken",
      "schenkt",
      "schenkte",
      "hat geschenkt"
    ],
    "examples": {
      "fa": [
        "Ich schenke dir ein Buch.",
        "من به تو یک کتاب هدیه می‌دهم."
      ],
      "en": [
        "Was schenkst du ihr?",
        "What are you giving her?"
      ]
    }
  },
  {
    "word": "das Buch",
    "translations": {
      "fa": "کتاب",
      "en": "book"
    },
    "explanation": {
      "fa": "مجموعه‌ای از صفحات چاپ‌شده با اطلاعات یا داستان.",
      "en": "A collection of printed pages with information or stories."
    },
    "conjugations": null,
    "examples": {
      "fa": [
        "Ich lese ein interessantes Buch.",
        "من یک کتاب جالب می‌خوانم."
      ],
      "en": [
        "Dieses Buch ist sehr spannend.",
        "This book is very exciting."
      ]
    }
  },
  {
    "word": "lesen",
    "translations": {
      "fa": "خواندن",
      "en": "to read"
    },
    "explanation": {
      "fa": "کلمات نوشته‌شده را دیدن و فهمیدن.",
      "en": "To look at and understand written words."
    },
    "conjugations": [
      "lesen",
      "liest",
      "las",
      "hat gelesen"
    ],
    "examples": {
      "fa": [
        "Ich lese gern Romane.",
        "من دوست دارم رمان بخوانم."
      ],
      "en": [
        "Liest du die Zeitung?",
        "Are you reading the newspaper?"
      ]
    }
  },
  {
    "word": "schreiben",
    "translations": {
      "fa": "نوشتن",
      "en": "to write"
    },
    "explanation": {
      "fa": "کلمات یا متن را روی کاغذ یا کامپیوتر ایجاد کردن.",
      "en": "To create words or text on paper or computer."
    },
    "conjugations": [
      "schreiben",
      "schreibt",
      "schrieb",
      "hat geschrieben"
    ],
    "examples": {
      "fa": [
        "Ich schreibe einen Brief.",
        "من یک نامه می‌نویسم."
      ],
      "en": [
        "Schreib mir eine Nachricht!",
        "Write me a message!"
      ]
    }
  },
  {
    "word": "der Brief",
    "translations": {
      "fa": "نامه",
      "en": "letter"
    },
    "explanation": {
      "fa": "پیام نوشته‌شده که معمولاً با پست ارسال می‌شود.",
      "en": "A written message usually sent by mail."
    },
    "conjugations": null,
    "examples": {
      "fa": [
        "Ich habe einen Brief bekommen.",
        "من یک نامه دریافت کردم."
      ],
      "en": [
        "Der Brief ist gestern angekommen.",
        "The letter arrived yesterday."
      ]
    }
  },
  {
    "word": "die Nachricht",
    "translations": {
      "fa": "پیام",
      "en": "message, news"
    },
    "explanation": {
      "fa": "اطلاعات یا پیامی که ارسال می‌شود.",
      "en": "Information or a message that is sent."
    },
    "conjugations": null,
    "examples": {
      "fa": [
        "Hast du meine Nachricht gelesen?",
        "پیام من را خواندی؟"
      ],
      "en": [
        "Ich habe gute Nachrichten!",
        "I have good news!"
      ]
    }
  },
  {
    "word": "anrufen",
    "translations": {
      "fa": "تلفن کردن",
      "en": "to call (on the phone)"
    },
    "explanation": {
      "fa": "با تلفن با کسی تماس گرفتن.",
      "en": "To contact someone by telephone."
    },
    "conjugations": [
      "anrufen",
      "ruft an",
      "rief an",
      "hat angerufen"
    ],
    "examples": {
      "fa": [
        "Ich rufe dich später an.",
        "من بعداً به تو زنگ می‌زنم."
      ],
      "en": [
        "Ruf mich an!",
        "Call me!"
      ]
    }
  },
  {
    "word": "das Telefon",
    "translations": {
      "fa": "تلفن",
      "en": "telephone, phone"
    },
    "explanation": {
      "fa": "دستگاهی برای مکالمه با افراد دور.",
      "en": "A device for talking to people far away."
    },
    "conjugations": null,
    "examples": {
      "fa": [
        "Das Telefon klingelt.",
        "تلفن زنگ می‌خورد."
      ],
      "en": [
        "Wo ist das Telefon?",
        "Where is the phone?"
      ]
    }
  },
  {
    "word": "hören",
    "translations": {
      "fa": "شنیدن",
      "en": "to hear, to listen"
    },
    "explanation": {
      "fa": "صدا را با گوش دریافت کردن.",
      "en": "To perceive sound with the ear."
    },
    "conjugations": [
      "hören",
      "hört",
      "hörte",
      "hat gehört"
    ],
    "examples": {
      "fa": [
        "Ich höre Musik.",
        "من دارم موسیقی گوش می‌دهم."
      ],
      "en": [
        "Hörst du das?",
        "Do you hear that?"
      ]
    }
  },
  {
    "word": "sehen",
    "translations": {
      "fa": "دیدن",
      "en": "to see"
    },
    "explanation": {
      "fa": "با چشم مشاهده کردن.",
      "en": "To perceive with the eyes."
    },
    "conjugations": [
      "sehen",
      "sieht",
      "sah",
      "hat gesehen"
    ],
    "examples": {
      "fa": [
        "Ich sehe dich!",
        "من تو را می‌بینم!"
      ],
      "en": [
        "Siehst du den Vogel?",
        "Do you see the bird?"
      ]
    }
  },
  {
    "word": "schauen",
    "translations": {
      "fa": "نگاه کردن",
      "en": "to look, to watch"
    },
    "explanation": {
      "fa": "با دقت به چیزی توجه کردن.",
      "en": "To direct attention to something with care."
    },
    "conjugations": [
      "schauen",
      "schaut",
      "schaute",
      "hat geschaut"
    ],
    "examples": {
      "fa": [
        "Schau mal!",
        "نگاه کن!"
      ],
      "en": [
        "Ich schaue gern Filme.",
        "I like to watch movies."
      ]
    }
  },
  {
    "word": "der Film",
    "translations": {
      "fa": "فیلم",
      "en": "film, movie"
    },
    "explanation": {
      "fa": "تصاویر متحرک که داستان می‌گویند.",
      "en": "Moving pictures that tell a story."
    },
    "conjugations": null,
    "examples": {
      "fa": [
        "Welchen Film möchtest du sehen?",
        "کدام فیلم را می‌خواهی ببینی؟"
      ],
      "en": [
        "Der Film war sehr gut.",
        "The movie was very good."
      ]
    }
  },
  {
    "word": "das Kino",
    "translations": {
      "fa": "سینما",
      "en": "cinema, movie theater"
    },
    "explanation": {
      "fa": "مکانی برای تماشای فیلم.",
      "en": "A place to watch movies."
    },
    "conjugations": null,
    "examples": {
      "fa": [
        "Gehen wir ins Kino?",
        "به سینما برویم؟"
      ],
      "en": [
        "Das Kino ist um die Ecke.",
        "The cinema is around the corner."
      ]
    }
  },
  {
    "word": "die Musik",
    "translations": {
      "fa": "موسیقی",
      "en": "music"
    },
    "explanation": {
      "fa": "صداهای هماهنگ و ملودیک.",
      "en": "Harmonious and melodic sounds."
    },
    "conjugations": null,
    "examples": {
      "fa": [
        "Ich liebe Musik.",
        "من عاشق موسیقی هستم."
      ],
      "en": [
        "Welche Musik hörst du gern?",
        "What music do you like to listen to?"
      ]
    }
  },
  {
    "word": "tanzen",
    "translations": {
      "fa": "رقصیدن",
      "en": "to dance"
    },
    "explanation": {
      "fa": "با موسیقی حرکت ریتمیک کردن.",
      "en": "To move rhythmically to music."
    },
    "conjugations": [
      "tanzen",
      "tanzt",
      "tanzte",
      "hat getanzt"
    ],
    "examples": {
      "fa": [
        "Lass uns tanzen!",
        "بیا برقصیم!"
      ],
      "en": [
        "Sie tanzt sehr gut.",
        "She dances very well."
      ]
    }
  },
  {
    "word": "singen",
    "translations": {
      "fa": "آواز خواندن",
      "en": "to sing"
    },
    "explanation": {
      "fa": "با صدا موسیقی ایجاد کردن.",
      "en": "To make music with the voice."
    },
    "conjugations": [
      "singen",
      "singt",
      "sang",
      "hat gesungen"
    ],
    "examples": {
      "fa": [
        "Er singt ein Lied.",
        "او یک آهنگ می‌خواند."
      ],
      "en": [
        "Singst du gern?",
        "Do you like to sing?"
      ]
    }
  },
  {
    "word": "das Lied",
    "translations": {
      "fa": "آهنگ، ترانه",
      "en": "song"
    },
    "explanation": {
      "fa": "قطعهٔ موسیقی با کلمات.",
      "en": "A piece of music with words."
    },
    "conjugations": null,
    "examples": {
      "fa": [
        "Das ist mein Lieblingslied.",
        "این آهنگ مورد علاقهٔ من است."
      ],
      "en": [
        "Kennst du dieses Lied?",
        "Do you know this song?"
      ]
    }
  },
  {
    "word": "das Hobby",
    "translations": {
      "fa": "سرگرمی",
      "en": "hobby"
    },
    "explanation": {
      "fa": "فعالیتی که در وقت آزاد برای لذت انجام می‌دهید.",
      "en": "An activity you do for pleasure in your free time."
    },
    "conjugations": null,
    "examples": {
      "fa": [
        "Was ist dein Hobby?",
        "سرگرمی تو چیست؟"
      ],
      "en": [
        "Mein Hobby ist Fotografieren.",
        "My hobby is photography."
      ]
    }
  },
  {
    "word": "die Freizeit",
    "translations": {
      "fa": "وقت آزاد",
      "en": "free time, leisure time"
    },
    "explanation": {
      "fa": "زمانی که از کار یا تعهدات آزاد هستید.",
      "en": "Time when you are free from work or obligations."
    },
    "conjugations": null,
    "examples": {
      "fa": [
        "In meiner Freizeit lese ich.",
        "من در وقت آزادم کتاب می‌خوانم."
      ],
      "en": [
        "Was machst du in deiner Freizeit?",
        "What do you do in your free time?"
      ]
    }
  },
  {
    "word": "entspannen",
    "translations": {
      "fa": "استراحت کردن",
      "en": "to relax"
    },
    "explanation": {
      "fa": "آرامش یافتن؛ استرس را کاهش دادن.",
      "en": "To become calm; to reduce stress."
    },
    "conjugations": [
      "entspannen",
      "entspannt",
      "entspannte",
      "hat entspannt"
    ],
    "examples": {
      "fa": [
        "Ich muss mich entspannen.",
        "من باید استراحت کنم."
      ],
      "en": [
        "Am Wochenende entspanne ich mich.",
        "On the weekend I relax."
      ]
    }
  },
  {
    "word": "der Stress",
    "translations": {
      "fa": "استرس",
      "en": "stress"
    },
    "explanation": {
      "fa": "فشار روحی یا جسمی.",
      "en": "Mental or physical pressure."
    },
    "conjugations": null,
    "examples": {
      "fa": [
        "Ich habe viel Stress.",
        "من استرس زیادی دارم."
      ],
      "en": [
        "Der Stress bei der Arbeit ist groß.",
        "The stress at work is high."
      ]
    }
  },
  {
    "word": "die Pause",
    "translations": {
      "fa": "استراحت، وقفه",
      "en": "break, pause"
    },
    "explanation": {
      "fa": "مدت زمان کوتاهی برای استراحت.",
      "en": "A short period for rest."
    },
    "conjugations": null,
    "examples": {
      "fa": [
        "Ich mache eine Pause.",
        "من یک استراحت می‌کنم."
      ],
      "en": [
        "Die Pause dauert 15 Minuten.",
        "The break lasts 15 minutes."
      ]
    }
  },
  {
    "word": "weitermachen",
    "translations": {
      "fa": "ادامه دادن",
      "en": "to continue"
    },
    "explanation": {
      "fa": "کاری را که شروع کرده‌اید ادامه دادن.",
      "en": "To go on with something you started."
    },
    "conjugations": [
      "weitermachen",
      "macht weiter",
      "machte weiter",
      "hat weitergemacht"
    ],
    "examples": {
      "fa": [
        "Wir machen nach der Pause weiter.",
        "ما بعد از استراحت ادامه می‌دهیم."
      ],
      "en": [
        "Mach weiter!",
        "Continue!"
      ]
    }
  },
  {
    "word": "aufhören",
    "translations": {
      "fa": "متوقف شدن",
      "en": "to stop"
    },
    "explanation": {
      "fa": "کاری را دیگر ادامه ندادن.",
      "en": "To no longer continue doing something."
    },
    "conjugations": [
      "aufhören",
      "hört auf",
      "hörte auf",
      "hat aufgehört"
    ],
    "examples": {
      "fa": [
        "Hör auf zu reden!",
        "دیگر حرف نزن!"
      ],
      "en": [
        "Es hat aufgehört zu regnen.",
        "It has stopped raining."
      ]
    }
  },
  {
    "word": "beginnen",
    "translations": {
      "fa": "شروع کردن",
      "en": "to begin, to start"
    },
    "explanation": {
      "fa": "کاری را آغاز کردن.",
      "en": "To start doing something."
    },
    "conjugations": [
      "beginnen",
      "beginnt",
      "begann",
      "hat begonnen"
    ],
    "examples": {
      "fa": [
        "Wann beginnt der Kurs?",
        "کلاس کی شروع می‌شود؟"
      ],
      "en": [
        "Lass uns beginnen!",
        "Let's begin!"
      ]
    }
  },
  {
    "word": "enden",
    "translations": {
      "fa": "تمام شدن",
      "en": "to end, to finish"
    },
    "explanation": {
      "fa": "به پایان رسیدن.",
      "en": "To come to a conclusion."
    },
    "conjugations": [
      "enden",
      "endet",
      "endete",
      "hat geendet"
    ],
    "examples": {
      "fa": [
        "Wann endet die Veranstaltung?",
        "رویداد کی تمام می‌شود؟"
      ],
      "en": [
        "Der Film endet um 22 Uhr.",
        "The movie ends at 10 PM."
      ]
    }
  },
  {
    "word": "mögen",
    "translations": {
      "fa": "دوست داشتن",
      "en": "to like"
    },
    "explanation": {
      "fa": "علاقه داشتن به چیزی یا کسی.",
      "en": "To have affection for something or someone."
    },
    "conjugations": [
      "mögen",
      "mag",
      "mochte",
      "hat gemocht"
    ],
    "examples": {
      "fa": [
        "Ich mag Schokolade.",
        "من شکلات را دوست دارم."
      ],
      "en": [
        "Magst du Pizza?",
        "Do you like pizza?"
      ]
    }
  },
  {
    "word": "lieben",
    "translations": {
      "fa": "عاشق بودن",
      "en": "to love"
    },
    "explanation": {
      "fa": "احساس عشق عمیق نسبت به کسی یا چیزی.",
      "en": "To feel deep affection for someone or something."
    },
    "conjugations": [
      "lieben",
      "liebt",
      "liebte",
      "hat geliebt"
    ],
    "examples": {
      "fa": [
        "Ich liebe dich.",
        "من تو را دوست دارم."
      ],
      "en": [
        "Sie liebt Tiere.",
        "She loves animals."
      ]
    }
  },
  {
    "word": "hassen",
    "translations": {
      "fa": "متنفر بودن",
      "en": "to hate"
    },
    "explanation": {
      "fa": "احساس بیزاری شدید نسبت به چیزی.",
      "en": "To feel intense dislike for something."
    },
    "conjugations": [
      "hassen",
      "hasst",
      "hasste",
      "hat gehasst"
    ],
    "examples": {
      "fa": [
        "Ich hasse Spinnen.",
        "من از عنکبوت متنفرم."
      ],
      "en": [
        "Er hasst den Winter.",
        "He hates winter."
      ]
    }
  },
  {
    "word": "brauchen",
    "translations": {
      "fa": "نیاز داشتن",
      "en": "to need"
    },
    "explanation": {
      "fa": "چیزی ضروری بودن.",
      "en": "To require something as necessary."
    },
    "conjugations": [
      "brauchen",
      "braucht",
      "brauchte",
      "hat gebraucht"
    ],
    "examples": {
      "fa": [
        "Ich brauche Hilfe.",
        "من به کمک نیاز دارم."
      ],
      "en": [
        "Was brauchst du?",
        "What do you need?"
      ]
    }
  },
  {
    "word": "wollen",
    "translations": {
      "fa": "خواستن",
      "en": "to want"
    },
    "explanation": {
      "fa": "تمایل یا آرزو داشتن برای چیزی.",
      "en": "To desire or wish for something."
    },
    "conjugations": [
      "wollen",
      "will",
      "wollte",
      "hat gewollt"
    ],
    "examples": {
      "fa": [
        "Ich will nach Hause gehen.",
        "من می‌خواهم به خانه بروم."
      ],
      "en": [
        "Was willst du essen?",
        "What do you want to eat?"
      ]
    }
  },
  {
    "word": "können",
    "translations": {
      "fa": "توانستن",
      "en": "can, to be able to"
    },
    "explanation": {
      "fa": "قابلیت یا توانایی انجام کاری را داشتن.",
      "en": "To have the ability or capability to do something."
    },
    "conjugations": [
      "können",
      "kann",
      "konnte",
      "hat gekonnt"
    ],
    "examples": {
      "fa": [
        "Ich kann Deutsch sprechen.",
        "من می‌توانم آلمانی صحبت کنم."
      ],
      "en": [
        "Kannst du mir helfen?",
        "Can you help me?"
      ]
    }
  },
  {
    "word": "müssen",
    "translations": {
      "fa": "مجبور بودن",
      "en": "must, to have to"
    },
    "explanation": {
      "fa": "الزام داشتن برای انجام کاری.",
      "en": "To be obligated to do something."
    },
    "conjugations": [
      "müssen",
      "muss",
      "musste",
      "hat gemusst"
    ],
    "examples": {
      "fa": [
        "Ich muss jetzt gehen.",
        "من باید الان بروم."
      ],
      "en": [
        "Du musst das machen.",
        "You must do that."
      ]
    }
  },
  {
    "word": "dürfen",
    "translations": {
      "fa": "اجازه داشتن",
      "en": "may, to be allowed to"
    },
    "explanation": {
      "fa": "مجوز یا اجازهٔ انجام کاری را داشتن.",
      "en": "To have permission to do something."
    },
    "conjugations": [
      "dürfen",
      "darf",
      "durfte",
      "hat gedurft"
    ],
    "examples": {
      "fa": [
        "Darf ich reinkommen?",
        "می‌توانم وارد شوم؟"
      ],
      "en": [
        "Du darfst hier nicht rauchen.",
        "You're not allowed to smoke here."
      ]
    }
  },
  {
    "word": "sollen",
    "translations": {
      "fa": "باید (توصیه)",
      "en": "should, to be supposed to"
    },
    "explanation": {
      "fa": "توصیه یا انتظار برای انجام کاری.",
      "en": "A recommendation or expectation to do something."
    },
    "conjugations": [
      "sollen",
      "soll",
      "sollte",
      "hat gesollt"
    ],
    "examples": {
      "fa": [
        "Du solltest mehr schlafen.",
        "تو باید بیشتر بخوابی."
      ],
      "en": [
        "Was soll ich machen?",
        "What should I do?"
      ]
    }
  },
  {
    "word": "werden",
    "translations": {
      "fa": "شدن",
      "en": "to become, will"
    },
    "explanation": {
      "fa": "تبدیل شدن به چیزی؛ فعل کمکی آینده.",
      "en": "To turn into something; auxiliary verb for future."
    },
    "conjugations": [
      "werden",
      "wird",
      "wurde",
      "ist geworden"
    ],
    "examples": {
      "fa": [
        "Ich werde Arzt.",
        "من دکتر می‌شوم."
      ],
      "en": [
        "Es wird kalt.",
        "It's getting cold."
      ]
    }
  },
  {
    "word": "bleiben",
    "translations": {
      "fa": "ماندن",
      "en": "to stay, to remain"
    },
    "explanation": {
      "fa": "در جایی یا وضعیتی باقی ماندن.",
      "en": "To continue in a place or condition."
    },
    "conjugations": [
      "bleiben",
      "bleibt",
      "blieb",
      "ist geblieben"
    ],
    "examples": {
      "fa": [
        "Ich bleibe zu Hause.",
        "من در خانه می‌مانم."
      ],
      "en": [
        "Bleib hier!",
        "Stay here!"
      ]
    }
  },
  {
    "word": "gehen",
    "translations": {
      "fa": "رفتن",
      "en": "to go"
    },
    "explanation": {
      "fa": "از یک مکان به مکان دیگر حرکت کردن.",
      "en": "To move from one place to another."
    },
    "conjugations": [
      "gehen",
      "geht",
      "ging",
      "ist gegangen"
    ],
    "examples": {
      "fa": [
        "Ich gehe zur Schule.",
        "من به مدرسه می‌روم."
      ],
      "en": [
        "Lass uns gehen!",
        "Let's go!"
      ]
    }
  },
  {
    "word": "kommen",
    "translations": {
      "fa": "آمدن",
      "en": "to come"
    },
    "explanation": {
      "fa": "به سمت جایی یا کسی حرکت کردن.",
      "en": "To move toward a place or person."
    },
    "conjugations": [
      "kommen",
      "kommt",
      "kam",
      "ist gekommen"
    ],
    "examples": {
      "fa": [
        "Komm her!",
        "بیا اینجا!"
      ],
      "en": [
        "Ich komme aus dem Iran.",
        "I come from Iran."
      ]
    }
  },
  {
    "word": "zurückkommen",
    "translations": {
      "fa": "برگشتن",
      "en": "to come back, to return"
    },
    "explanation": {
      "fa": "به مکان قبلی بازگشتن.",
      "en": "To return to a previous location."
    },
    "conjugations": [
      "zurückkommen",
      "kommt zurück",
      "kam zurück",
      "ist zurückgekommen"
    ],
    "examples": {
      "fa": [
        "Wann kommst du zurück?",
        "کی برمی‌گردی؟"
      ],
      "en": [
        "Ich komme bald zurück.",
        "I'll be back soon."
      ]
    }
  },
  {
    "word": "bringen",
    "translations": {
      "fa": "آوردن",
      "en": "to bring"
    },
    "explanation": {
      "fa": "چیزی را با خود حمل کردن.",
      "en": "To carry something with you."
    },
    "conjugations": [
      "bringen",
      "bringt",
      "brachte",
      "hat gebracht"
    ],
    "examples": {
      "fa": [
        "Bring mir bitte ein Glas Wasser.",
        "لطفاً یک لیوان آب برایم بیاور."
      ],
      "en": [
        "Was hast du mitgebracht?",
        "What did you bring?"
      ]
    }
  },
  {
    "word": "nehmen",
    "translations": {
      "fa": "گرفتن",
      "en": "to take"
    },
    "explanation": {
      "fa": "چیزی را برداشتن یا دریافت کردن.",
      "en": "To pick up or receive something."
    },
    "conjugations": [
      "nehmen",
      "nimmt",
      "nahm",
      "hat genommen"
    ],
    "examples": {
      "fa": [
        "Nimm einen Apfel!",
        "یک سیب بردار!"
      ],
      "en": [
        "Ich nehme den Bus.",
        "I'm taking the bus."
      ]
    }
  },
  {
    "word": "geben",
    "translations": {
      "fa": "دادن",
      "en": "to give"
    },
    "explanation": {
      "fa": "چیزی را به کسی تحویل دادن.",
      "en": "To hand something to someone."
    },
    "conjugations": [
      "geben",
      "gibt",
      "gab",
      "hat gegeben"
    ],
    "examples": {
      "fa": [
        "Gib mir das Buch!",
        "کتاب را به من بده!"
      ],
      "en": [
        "Es gibt viele Möglichkeiten.",
        "There are many possibilities."
      ]
    }
  },
  {
    "word": "zeigen",
    "translations": {
      "fa": "نشان دادن",
      "en": "to show"
    },
    "explanation": {
      "fa": "چیزی را قابل دیدن کردن.",
      "en": "To make something visible."
    },
    "conjugations": [
      "zeigen",
      "zeigt",
      "zeigte",
      "hat gezeigt"
    ],
    "examples": {
      "fa": [
        "Zeig mir dein Foto!",
        "عکست را به من نشان بده!"
      ],
      "en": [
        "Ich zeige dir den Weg.",
        "I'll show you the way."
      ]
    }
  },
  {
    "word": "erklären",
    "translations": {
      "fa": "توضیح دادن",
      "en": "to explain"
    },
    "explanation": {
      "fa": "چیزی را واضح و قابل فهم کردن.",
      "en": "To make something clear and understandable."
    },
    "conjugations": [
      "erklären",
      "erklärt",
      "erklärte",
      "hat erklärt"
    ],
    "examples": {
      "fa": [
        "Kannst du das erklären?",
        "می‌توانی این را توضیح دهی؟"
      ],
      "en": [
        "Der Lehrer erklärt die Grammatik.",
        "The teacher explains the grammar."
      ]
    }
  },
  {
    "word": "fragen",
    "translations": {
      "fa": "سؤال کردن",
      "en": "to ask"
    },
    "explanation": {
      "fa": "برای دریافت اطلاعات سؤال مطرح کردن.",
      "en": "To pose a question to get information."
    },
    "conjugations": [
      "fragen",
      "fragt",
      "fragte",
      "hat gefragt"
    ],
    "examples": {
      "fa": [
        "Darf ich dich etwas fragen?",
        "می‌توانم چیزی از تو بپرسم؟"
      ],
      "en": [
        "Frag ihn!",
        "Ask him!"
      ]
    }
  },
  {
    "word": "antworten",
    "translations": {
      "fa": "پاسخ دادن",
      "en": "to answer"
    },
    "explanation": {
      "fa": "به سؤال یا درخواست پاسخ دادن.",
      "en": "To respond to a question or request."
    },
    "conjugations": [
      "antworten",
      "antwortet",
      "antwortete",
      "hat geantwortet"
    ],
    "examples": {
      "fa": [
        "Antworte bitte!",
        "لطفاً پاسخ بده!"
      ],
      "en": [
        "Er antwortet nicht.",
        "He's not answering."
      ]
    }
  },
  {
    "word": "sagen",
    "translations": {
      "fa": "گفتن",
      "en": "to say, to tell"
    },
    "explanation": {
      "fa": "کلمات یا اطلاعات را بیان کردن.",
      "en": "To express words or information."
    },
    "conjugations": [
      "sagen",
      "sagt",
      "sagte",
      "hat gesagt"
    ],
    "examples": {
      "fa": [
        "Was sagst du?",
        "چه می‌گویی؟"
      ],
      "en": [
        "Sag mir die Wahrheit!",
        "Tell me the truth!"
      ]
    }
  },
  {
    "word": "erzählen",
    "translations": {
      "fa": "تعریف کردن",
      "en": "to tell (a story)"
    },
    "explanation": {
      "fa": "داستان یا رویداد را شرح دادن.",
      "en": "To narrate a story or event."
    },
    "conjugations": [
      "erzählen",
      "erzählt",
      "erzählte",
      "hat erzählt"
    ],
    "examples": {
      "fa": [
        "Erzähl mir von deinem Urlaub!",
        "از تعطیلاتت برایم بگو!"
      ],
      "en": [
        "Sie erzählt eine Geschichte.",
        "She's telling a story."
      ]
    }
  },
  {
    "word": "die Geschichte",
    "translations": {
      "fa": "داستان، تاریخ",
      "en": "story, history"
    },
    "explanation": {
      "fa": "روایت رویدادها یا حوادث گذشته.",
      "en": "A narrative of events or past occurrences."
    },
    "conjugations": null,
    "examples": {
      "fa": [
        "Das ist eine interessante Geschichte.",
        "این یک داستان جالب است."
      ],
      "en": [
        "Ich studiere Geschichte.",
        "I study history."
      ]
    }
  },
  {
    "word": "die Zukunft",
    "translations": {
      "fa": "آینده",
      "en": "future"
    },
    "explanation": {
      "fa": "زمانی که هنوز نیامده است.",
      "en": "The time that has not yet come."
    },
    "conjugations": null,
    "examples": {
      "fa": [
        "Was sind deine Pläne für die Zukunft?",
        "برنامه‌های تو برای آینده چیست؟"
      ],
      "en": [
        "In der Zukunft möchte ich reisen.",
        "In the future I want to travel."
      ]
    }
  },
  {
    "word": "die Vergangenheit",
    "translations": {
      "fa": "گذشته",
      "en": "past"
    },
    "explanation": {
      "fa": "زمانی که قبلاً گذشته است.",
      "en": "The time that has already passed."
    },
    "conjugations": null,
    "examples": {
      "fa": [
        "Das ist Vergangenheit.",
        "آن گذشته است."
      ],
      "en": [
        "Wir sollten nicht in der Vergangenheit leben.",
        "We shouldn't live in the past."
      ]
    }
  },
  {
    "word": "die Gegenwart",
    "translations": {
      "fa": "حال، زمان حاضر",
      "en": "present"
    },
    "explanation": {
      "fa": "زمان کنونی؛ الان.",
      "en": "The current time; now."
    },
    "conjugations": null,
    "examples": {
      "fa": [
        "Lebe in der Gegenwart!",
        "در زمان حاضر زندگی کن!"
      ],
      "en": [
        "Die Gegenwart ist wichtig.",
        "The present is important."
      ]
    }
  },
  {
    "word": "der Moment",
    "translations": {
      "fa": "لحظه",
      "en": "moment"
    },
    "explanation": {
      "fa": "مدت زمان بسیار کوتاه.",
      "en": "A very short period of time."
    },
    "conjugations": null,
    "examples": {
      "fa": [
        "Einen Moment, bitte!",
        "یک لحظه، لطفاً!"
      ],
      "en": [
        "Das war ein schöner Moment.",
        "That was a beautiful moment."
      ]
    }
  },
  {
    "word": "heute",
    "translations": {
      "fa": "امروز",
      "en": "today"
    },
    "explanation": {
      "fa": "در این روز.",
      "en": "On this day."
    },
    "conjugations": null,
    "examples": {
      "fa": [
        "Was machst du heute?",
        "امروز چه می‌کنی؟"
      ],
      "en": [
        "Heute ist ein schöner Tag.",
        "Today is a beautiful day."
      ]
    }
  },
  {
    "word": "morgen",
    "translations": {
      "fa": "فردا",
      "en": "tomorrow"
    },
    "explanation": {
      "fa": "روز بعد از امروز.",
      "en": "The day after today."
    },
    "conjugations": null,
    "examples": {
      "fa": [
        "Bis morgen!",
        "تا فردا!"
      ],
      "en": [
        "Ich sehe dich morgen.",
        "I'll see you tomorrow."
      ]
    }
  },
  {
    "word": "gestern",
    "translations": {
      "fa": "دیروز",
      "en": "yesterday"
    },
    "explanation": {
      "fa": "روز قبل از امروز.",
      "en": "The day before today."
    },
    "conjugations": null,
    "examples": {
      "fa": [
        "Ich war gestern im Kino.",
        "من دیروز در سینما بودم."
      ],
      "en": [
        "Gestern war Sonntag.",
        "Yesterday was Sunday."
      ]
    }
  },
  {
    "word": "jetzt",
    "translations": {
      "fa": "الان، اکنون",
      "en": "now"
    },
    "explanation": {
      "fa": "در این لحظه.",
      "en": "At this moment."
    },
    "conjugations": null,
    "examples": {
      "fa": [
        "Ich muss jetzt gehen.",
        "من باید الان بروم."
      ],
      "en": [
        "Was machst du jetzt?",
        "What are you doing now?"
      ]
    }
  },
  {
    "word": "immer",
    "translations": {
      "fa": "همیشه",
      "en": "always"
    },
    "explanation": {
      "fa": "در تمام مواقع.",
      "en": "At all times."
    },
    "conjugations": null,
    "examples": {
      "fa": [
        "Ich denke immer an dich.",
        "من همیشه به تو فکر می‌کنم."
      ],
      "en": [
        "Er kommt immer zu spät.",
        "He always comes late."
      ]
    }
  },
  {
    "word": "nie",
    "translations": {
      "fa": "هرگز",
      "en": "never"
    },
    "explanation": {
      "fa": "در هیچ زمانی نه.",
      "en": "Not at any time."
    },
    "conjugations": null,
    "examples": {
      "fa": [
        "Ich war nie in Paris.",
        "من هرگز در پاریس نبوده‌ام."
      ],
      "en": [
        "Sag niemals nie!",
        "Never say never!"
      ]
    }
  },
  {
    "word": "manchmal",
    "translations": {
      "fa": "گاهی اوقات",
      "en": "sometimes"
    },
    "explanation": {
      "fa": "در برخی از مواقع.",
      "en": "On some occasions."
    },
    "conjugations": null,
    "examples": {
      "fa": [
        "Manchmal bin ich müde.",
        "گاهی اوقات خسته هستم."
      ],
      "en": [
        "Er kommt manchmal zu spät.",
        "He sometimes comes late."
      ]
    }
  },
  {
    "word": "oft",
    "translations": {
      "fa": "اغلب، اکثر اوقات",
      "en": "often"
    },
    "explanation": {
      "fa": "در بسیاری از مواقع.",
      "en": "On many occasions."
    },
    "conjugations": null,
    "examples": {
      "fa": [
        "Ich gehe oft ins Kino.",
        "من اغلب به سینما می‌روم."
      ],
      "en": [
        "Wie oft machst du Sport?",
        "How often do you exercise?"
      ]
    }
  },
  {
    "word": "selten",
    "translations": {
      "fa": "به ندرت",
      "en": "rarely, seldom"
    },
    "explanation": {
      "fa": "در تعداد کمی از مواقع.",
      "en": "On a few occasions."
    },
    "conjugations": null,
    "examples": {
      "fa": [
        "Ich esse selten Fast Food.",
        "من به ندرت فست فود می‌خورم."
      ],
      "en": [
        "Er ist selten krank.",
        "He is rarely sick."
      ]
    }
  },
  {
    "word": "die Erfahrung",
    "translations": {
      "fa": "تجربه",
      "en": "experience"
    },
    "explanation": {
      "fa": "دانش یا مهارتی که از انجام چیزی به دست می‌آید.",
      "en": "Knowledge or skill gained from doing something."
    },
    "conjugations": null,
    "examples": {
      "fa": [
        "Ich habe viel Erfahrung in diesem Bereich.",
        "من تجربه زیادی در این زمینه دارم."
      ],
      "en": [
        "Sie sammelt neue Erfahrungen.",
        "She is gaining new experiences."
      ]
    }
  },
  {
    "word": "entscheiden",
    "translations": {
      "fa": "تصمیم گرفتن",
      "en": "to decide"
    },
    "explanation": {
      "fa": "انتخاب کردن بین گزینه‌های مختلف.",
      "en": "To make a choice between different options."
    },
    "conjugations": [
      "entscheiden",
      "entscheidet",
      "entschied",
      "hat entschieden"
    ],
    "examples": {
      "fa": [
        "Ich muss mich schnell entscheiden.",
        "من باید سریع تصمیم بگیرم."
      ],
      "en": [
        "Wir haben uns für dieses Hotel entschieden.",
        "We decided on this hotel."
      ]
    }
  },
  {
    "word": "das Ergebnis",
    "translations": {
      "fa": "نتیجه",
      "en": "result"
    },
    "explanation": {
      "fa": "آنچه که از یک عمل یا فرآیند حاصل می‌شود.",
      "en": "What comes from an action or process."
    },
    "conjugations": null,
    "examples": {
      "fa": [
        "Das Ergebnis der Prüfung war gut.",
        "نتیجه آزمون خوب بود."
      ],
      "en": [
        "Wir warten auf das Ergebnis.",
        "We're waiting for the result."
      ]
    }
  },
  {
    "word": "der Unterschied",
    "translations": {
      "fa": "تفاوت",
      "en": "difference"
    },
    "explanation": {
      "fa": "آنچه که دو چیز را متفاوت می‌کند.",
      "en": "What makes two things different."
    },
    "conjugations": null,
    "examples": {
      "fa": [
        "Was ist der Unterschied zwischen diesen beiden?",
        "تفاوت بین این دو چیست؟"
      ],
      "en": [
        "Es gibt einen großen Unterschied.",
        "There is a big difference."
      ]
    }
  },
  {
    "word": "vergleichen",
    "translations": {
      "fa": "مقایسه کردن",
      "en": "to compare"
    },
    "explanation": {
      "fa": "شباهت‌ها و تفاوت‌های دو چیز را بررسی کردن.",
      "en": "To examine similarities and differences between two things."
    },
    "conjugations": [
      "vergleichen",
      "vergleicht",
      "verglich",
      "hat verglichen"
    ],
    "examples": {
      "fa": [
        "Ich vergleiche die Preise.",
        "من قیمت‌ها را مقایسه می‌کنم."
      ],
      "en": [
        "Man kann die zwei Produkte nicht vergleichen.",
        "You cannot compare the two products."
      ]
    }
  },
  {
    "word": "das Ziel",
    "translations": {
      "fa": "هدف",
      "en": "goal"
    },
    "explanation": {
      "fa": "چیزی که می‌خواهید به آن برسید.",
      "en": "Something you want to achieve."
    },
    "conjugations": null,
    "examples": {
      "fa": [
        "Mein Ziel ist es, Deutsch zu lernen.",
        "هدف من یادگیری آلمانی است."
      ],
      "en": [
        "Wir haben unser Ziel erreicht.",
        "We have reached our goal."
      ]
    }
  },
  {
    "word": "entwickeln",
    "translations": {
      "fa": "توسعه دادن",
      "en": "to develop"
    },
    "explanation": {
      "fa": "رشد کردن یا چیزی جدید ایجاد کردن.",
      "en": "To grow or create something new."
    },
    "conjugations": [
      "entwickeln",
      "entwickelt",
      "entwickelte",
      "hat entwickelt"
    ],
    "examples": {
      "fa": [
        "Die Firma entwickelt neue Produkte.",
        "شرکت محصولات جدید توسعه می‌دهد."
      ],
      "en": [
        "Er entwickelt seine Fähigkeiten weiter.",
        "He continues to develop his skills."
      ]
    }
  },
  {
    "word": "die Lösung",
    "translations": {
      "fa": "راه‌حل",
      "en": "solution"
    },
    "explanation": {
      "fa": "پاسخ به یک مشکل.",
      "en": "Answer to a problem."
    },
    "conjugations": null,
    "examples": {
      "fa": [
        "Wir suchen eine Lösung.",
        "ما به دنبال یک راه‌حل هستیم."
      ],
      "en": [
        "Das ist die beste Lösung.",
        "That is the best solution."
      ]
    }
  },
  {
    "word": "vorbereiten",
    "translations": {
      "fa": "آماده کردن",
      "en": "to prepare"
    },
    "explanation": {
      "fa": "چیزی را برای استفاده یا رویداد آینده آماده کردن.",
      "en": "To make something ready for use or a future event."
    },
    "conjugations": [
      "vorbereiten",
      "bereitet vor",
      "bereitete vor",
      "hat vorbereitet"
    ],
    "examples": {
      "fa": [
        "Ich bereite das Abendessen vor.",
        "من شام را آماده می‌کنم."
      ],
      "en": [
        "Sie bereitet sich auf die Prüfung vor.",
        "She is preparing for the exam."
      ]
    }
  },
  {
    "word": "die Vorbereitung",
    "translations": {
      "fa": "آماده‌سازی",
      "en": "preparation"
    },
    "explanation": {
      "fa": "فرآیند آماده شدن برای چیزی.",
      "en": "The process of getting ready for something."
    },
    "conjugations": null,
    "examples": {
      "fa": [
        "Die Vorbereitung dauert lange.",
        "آماده‌سازی زمان می‌برد."
      ],
      "en": [
        "Gute Vorbereitung ist wichtig.",
        "Good preparation is important."
      ]
    }
  },
  {
    "word": "benutzen",
    "translations": {
      "fa": "استفاده کردن",
      "en": "to use"
    },
    "explanation": {
      "fa": "از چیزی برای هدفی استفاده کردن.",
      "en": "To use something for a purpose."
    },
    "conjugations": [
      "benutzen",
      "benutzt",
      "benutzte",
      "hat benutzt"
    ],
    "examples": {
      "fa": [
        "Ich benutze mein Handy jeden Tag.",
        "من هر روز از گوشی‌ام استفاده می‌کنم."
      ],
      "en": [
        "Darf ich deinen Stift benutzen?",
        "May I use your pen?"
      ]
    }
  },
  {
    "word": "das Werkzeug",
    "translations": {
      "fa": "ابزار",
      "en": "tool"
    },
    "explanation": {
      "fa": "وسیله‌ای برای انجام کار.",
      "en": "An instrument for doing work."
    },
    "conjugations": null,
    "examples": {
      "fa": [
        "Ich brauche das richtige Werkzeug.",
        "من به ابزار مناسب نیاز دارم."
      ],
      "en": [
        "Wo ist mein Werkzeug?",
        "Where is my tool?"
      ]
    }
  },
  {
    "word": "reparieren",
    "translations": {
      "fa": "تعمیر کردن",
      "en": "to repair"
    },
    "explanation": {
      "fa": "چیز خراب شده را درست کردن.",
      "en": "To fix something that is broken."
    },
    "conjugations": [
      "reparieren",
      "repariert",
      "reparierte",
      "hat repariert"
    ],
    "examples": {
      "fa": [
        "Ich muss mein Fahrrad reparieren.",
        "من باید دوچرخه‌ام را تعمیر کنم."
      ],
      "en": [
        "Kannst du das reparieren?",
        "Can you repair that?"
      ]
    }
  },
  {
    "word": "die Umwelt",
    "translations": {
      "fa": "محیط زیست",
      "en": "environment"
    },
    "explanation": {
      "fa": "طبیعت و جهان پیرامون ما.",
      "en": "Nature and the world around us."
    },
    "conjugations": null,
    "examples": {
      "fa": [
        "Wir müssen die Umwelt schützen.",
        "ما باید از محیط زیست محافظت کنیم."
      ],
      "en": [
        "Die Umwelt ist wichtig.",
        "The environment is important."
      ]
    }
  },
  {
    "word": "das Klima",
    "translations": {
      "fa": "آب و هوا",
      "en": "climate"
    },
    "explanation": {
      "fa": "شرایط جوی معمول یک منطقه.",
      "en": "The usual weather conditions of a region."
    },
    "conjugations": null,
    "examples": {
      "fa": [
        "Das Klima ändert sich.",
        "آب و هوا در حال تغییر است."
      ],
      "en": [
        "Hier ist das Klima mild.",
        "The climate here is mild."
      ]
    }
  },
  {
    "word": "die Luft",
    "translations": {
      "fa": "هوا",
      "en": "air"
    },
    "explanation": {
      "fa": "گاز اطراف ما که نفس می‌کشیم.",
      "en": "The gas around us that we breathe."
    },
    "conjugations": null,
    "examples": {
      "fa": [
        "Die Luft ist frisch.",
        "هوا تازه است."
      ],
      "en": [
        "Ich brauche frische Luft.",
        "I need fresh air."
      ]
    }
  },
  {
    "word": "der Baum",
    "translations": {
      "fa": "درخت",
      "en": "tree"
    },
    "explanation": {
      "fa": "گیاه بزرگ چوبی با تنه و شاخه‌ها.",
      "en": "A large woody plant with trunk and branches."
    },
    "conjugations": null,
    "examples": {
      "fa": [
        "Der Baum ist sehr alt.",
        "درخت خیلی قدیمی است."
      ],
      "en": [
        "Im Park gibt es viele Bäume.",
        "There are many trees in the park."
      ]
    }
  },
  {
    "word": "der Wald",
    "translations": {
      "fa": "جنگل",
      "en": "forest"
    },
    "explanation": {
      "fa": "منطقه بزرگی پوشیده از درختان.",
      "en": "A large area covered with trees."
    },
    "conjugations": null,
    "examples": {
      "fa": [
        "Wir gehen in den Wald spazieren.",
        "ما در جنگل قدم می‌زنیم."
      ],
      "en": [
        "Der Wald ist grün.",
        "The forest is green."
      ]
    }
  },
  {
    "word": "der Fluss",
    "translations": {
      "fa": "رودخانه",
      "en": "river"
    },
    "explanation": {
      "fa": "جریان بزرگ آب که به دریا می‌ریزد.",
      "en": "A large flow of water that runs to the sea."
    },
    "conjugations": null,
    "examples": {
      "fa": [
        "Der Fluss ist breit.",
        "رودخانه پهن است."
      ],
      "en": [
        "Wir schwimmen im Fluss.",
        "We swim in the river."
      ]
    }
  },
  {
    "word": "der Berg",
    "translations": {
      "fa": "کوه",
      "en": "mountain"
    },
    "explanation": {
      "fa": "ارتفاع طبیعی بسیار بلند زمین.",
      "en": "A very high natural elevation of land."
    },
    "conjugations": null,
    "examples": {
      "fa": [
        "Der Berg ist hoch.",
        "کوه بلند است."
      ],
      "en": [
        "Wir wandern auf den Berg.",
        "We hike up the mountain."
      ]
    }
  },
  {
    "word": "das Meer",
    "translations": {
      "fa": "دریا",
      "en": "sea"
    },
    "explanation": {
      "fa": "مساحت بزرگ آب شور.",
      "en": "A large area of salt water."
    },
    "conjugations": null,
    "examples": {
      "fa": [
        "Das Meer ist blau.",
        "دریا آبی است."
      ],
      "en": [
        "Ich liebe das Meer.",
        "I love the sea."
      ]
    }
  },
  {
    "word": "die Sonne",
    "translations": {
      "fa": "خورشید",
      "en": "sun"
    },
    "explanation": {
      "fa": "ستاره‌ای که به زمین نور و گرما می‌دهد.",
      "en": "The star that gives light and heat to Earth."
    },
    "conjugations": null,
    "examples": {
      "fa": [
        "Die Sonne scheint heute.",
        "امروز خورشید می‌تابد."
      ],
      "en": [
        "Die Sonne geht auf.",
        "The sun is rising."
      ]
    }
  },
  {
    "word": "der Regen",
    "translations": {
      "fa": "باران",
      "en": "rain"
    },
    "explanation": {
      "fa": "آب که از آسمان می‌بارد.",
      "en": "Water that falls from the sky."
    },
    "conjugations": null,
    "examples": {
      "fa": [
        "Es regnet heute.",
        "امروز باران می‌بارد."
      ],
      "en": [
        "Der Regen ist stark.",
        "The rain is heavy."
      ]
    }
  },
  {
    "word": "der Schnee",
    "translations": {
      "fa": "برف",
      "en": "snow"
    },
    "explanation": {
      "fa": "دانه‌های سفید یخ که از آسمان می‌بارند.",
      "en": "White frozen flakes that fall from the sky."
    },
    "conjugations": null,
    "examples": {
      "fa": [
        "Im Winter fällt Schnee.",
        "در زمستان برف می‌بارد."
      ],
      "en": [
        "Der Schnee ist weiß.",
        "The snow is white."
      ]
    }
  },
  {
    "word": "der Wind",
    "translations": {
      "fa": "باد",
      "en": "wind"
    },
    "explanation": {
      "fa": "هوای در حال حرکت.",
      "en": "Moving air."
    },
    "conjugations": null,
    "examples": {
      "fa": [
        "Der Wind ist stark heute.",
        "امروز باد قوی است."
      ],
      "en": [
        "Der Wind weht.",
        "The wind is blowing."
      ]
    }
  },
  {
    "word": "das Gewitter",
    "translations": {
      "fa": "طوفان رعد و برق",
      "en": "thunderstorm"
    },
    "explanation": {
      "fa": "طوفان با رعد و برق.",
      "en": "A storm with thunder and lightning."
    },
    "conjugations": null,
    "examples": {
      "fa": [
        "Es kommt ein Gewitter.",
        "طوفان در راه است."
      ],
      "en": [
        "Das Gewitter war laut.",
        "The thunderstorm was loud."
      ]
    }
  },
  {
    "word": "die Wolke",
    "translations": {
      "fa": "ابر",
      "en": "cloud"
    },
    "explanation": {
      "fa": "توده سفید یا خاکستری در آسمان.",
      "en": "A white or gray mass in the sky."
    },
    "conjugations": null,
    "examples": {
      "fa": [
        "Am Himmel sind viele Wolken.",
        "ابرهای زیادی در آسمان هستند."
      ],
      "en": [
        "Die Wolken sind dunkel.",
        "The clouds are dark."
      ]
    }
  },
  {
    "word": "die Jahreszeit",
    "translations": {
      "fa": "فصل",
      "en": "season"
    },
    "explanation": {
      "fa": "یکی از چهار دوره سال: بهار، تابستان، پاییز، زمستان.",
      "en": "One of the four periods of the year: spring, summer, fall, winter."
    },
    "conjugations": null,
    "examples": {
      "fa": [
        "Welche Jahreszeit magst du?",
        "کدام فصل را دوست داری؟"
      ],
      "en": [
        "Jede Jahreszeit ist schön.",
        "Every season is beautiful."
      ]
    }
  },
  {
    "word": "kalt",
    "translations": {
      "fa": "سرد",
      "en": "cold"
    },
    "explanation": {
      "fa": "دارای دمای پایین.",
      "en": "Having a low temperature."
    },
    "conjugations": null,
    "examples": {
      "fa": [
        "Es ist heute sehr kalt.",
        "امروز خیلی سرد است."
      ],
      "en": [
        "Das Wasser ist kalt.",
        "The water is cold."
      ]
    }
  },
  {
    "word": "warm",
    "translations": {
      "fa": "گرم",
      "en": "warm"
    },
    "explanation": {
      "fa": "دارای دمای خوشایند، نه خیلی گرم و نه خیلی سرد.",
      "en": "Having a pleasant temperature, not too hot or cold."
    },
    "conjugations": null,
    "examples": {
      "fa": [
        "Das Wetter ist warm.",
        "هوا گرم است."
      ],
      "en": [
        "Mir ist warm.",
        "I feel warm."
      ]
    }
  },
  {
    "word": "heiß",
    "translations": {
      "fa": "داغ",
      "en": "hot"
    },
    "explanation": {
      "fa": "دارای دمای بسیار بالا.",
      "en": "Having a very high temperature."
    },
    "conjugations": null,
    "examples": {
      "fa": [
        "Im Sommer ist es heiß.",
        "در تابستان هوا داغ است."
      ],
      "en": [
        "Der Kaffee ist heiß.",
        "The coffee is hot."
      ]
    }
  },
  {
    "word": "trocken",
    "translations": {
      "fa": "خشک",
      "en": "dry"
    },
    "explanation": {
      "fa": "بدون آب یا رطوبت.",
      "en": "Without water or moisture."
    },
    "conjugations": null,
    "examples": {
      "fa": [
        "Die Luft ist trocken.",
        "هوا خشک است."
      ],
      "en": [
        "Das Wetter bleibt trocken.",
        "The weather stays dry."
      ]
    }
  },
  {
    "word": "nass",
    "translations": {
      "fa": "خیس",
      "en": "wet"
    },
    "explanation": {
      "fa": "پوشیده از آب یا مایع.",
      "en": "Covered with water or liquid."
    },
    "conjugations": null,
    "examples": {
      "fa": [
        "Meine Schuhe sind nass.",
        "کفش‌هایم خیس هستند."
      ],
      "en": [
        "Das Gras ist nass.",
        "The grass is wet."
      ]
    }
  }
]