[
  {
    "id": "universal_a1_121_ru",
    "word": "всегда",
    "translations": {
      "en": "always",
      "de": "immer",
      "ar": "دائما",
      "fr": "toujours",
      "it": "sempre",
      "ru": "всегда",
      "es": "siempre",
      "pl": "zawsze",
      "fa": "همیشه"
    },
    "examples": [
      "Всегда так.",
      "Всегда хорошо.",
      "Всегда плохо.",
      "Всегда рад.",
      "Всегда готов.",
      "Я всегда здесь.",
      "Ты всегда прав.",
      "Он всегда опаздывает.",
      "Она всегда пунктуальна.",
      "Мы всегда вместе.",
      "Вы всегда заняты.",
      "Они всегда счастливы.",
      "Всегда помню.",
      "Всегда знал.",
      "Всегда думал.",
      "Всегда верил.",
      "Всегда надеялся.",
      "Всегда любил.",
      "Всегда буду помнить.",
      "Всегда буду любить.",
      "Почти всегда.",
      "Не всегда.",
      "Как всегда.",
      "Навсегда.",
      "На всегда.",
      "Всегда пожалуйста!",
      "Всегда ваш."
    ]
  },
  {
    "id": "universal_a1_122_ru",
    "word": "никогда",
    "translations": {
      "en": "never",
      "de": "nie, niemals",
      "ar": "أبدا",
      "fr": "jamais",
      "it": "mai",
      "ru": "никогда",
      "es": "nunca, jamás",
      "pl": "nigdy",
      "fa": "هرگز"
    },
    "examples": [
      "Никогда не говори никогда.",
      "Никогда не поздно.",
      "Никогда не рано.",
      "Я никогда не был там.",
      "Ты никогда не знаешь.",
      "Он никогда не опаздывает.",
      "Она никогда не врёт.",
      "Мы никогда не сдаёмся.",
      "Вы никогда не слушаете.",
      "Они никогда не приходят.",
      "Никогда не думал.",
      "Никогда не верил.",
      "Никогда не надеялся.",
      "Никогда не забуду.",
      "Никогда не прощу.",
      "Никогда больше.",
      "Никогда в жизни.",
      "Почти никогда.",
      "Практически никогда.",
      "Лучше поздно, чем никогда.",
      "Сейчас или никогда.",
      "Никогда не сдавайся!",
      "Никогда не говори умри.",
      "Ничего и никогда.",
      "Никогда такого не было.",
      "И никогда не будет.",
      "Никогда-никогда."
    ]
  },
  {
    "id": "universal_a1_123_ru",
    "word": "часто",
    "translations": {
      "en": "often",
      "de": "oft",
      "ar": "غالبا، كثيرا",
      "fr": "souvent",
      "it": "spesso",
      "ru": "часто",
      "es": "a menudo, frecuentemente",
      "pl": "często",
      "fa": "اغلب، مکرر"
    },
    "examples": [
      "Часто бываю здесь.",
      "Часто думаю о тебе.",
      "Часто вспоминаю.",
      "Я часто здесь.",
      "Ты часто опаздываешь.",
      "Он часто звонит.",
      "Она часто улыбается.",
      "Мы часто встречаемся.",
      "Вы часто путешествуете.",
      "Они часто ссорятся.",
      "Часто хожу в кино.",
      "Часто читаю книги.",
      "Часто слушаю музыку.",
      "Как часто?",
      "Слишком часто.",
      "Очень часто.",
      "Довольно часто.",
      "Не очень часто.",
      "Не так часто.",
      "Чаще всего.",
      "Чаще обычного.",
      "Всё чаще.",
      "Чаще и чаще.",
      "Реже и реже.",
      "Частенько бываю.",
      "Как можно чаще.",
      "Почаще приходи."
    ]
  },
  {
    "id": "universal_a1_124_ru",
    "word": "редко",
    "translations": {
      "en": "rarely, seldom",
      "de": "selten",
      "ar": "نادرا",
      "fr": "rarement",
      "it": "raramente",
      "ru": "редко",
      "es": "raramente, rara vez",
      "pl": "rzadko",
      "fa": "به ندرت"
    },
    "examples": [
      "Редко бываю здесь.",
      "Редко думаю об этом.",
      "Редко вспоминаю.",
      "Я редко здесь.",
      "Ты редко звонишь.",
      "Он редко приходит.",
      "Она редко улыбается.",
      "Мы редко встречаемся.",
      "Вы редко пишете.",
      "Они редко выходят.",
      "Редко хожу в театр.",
      "Редко читаю газеты.",
      "Редко смотрю телевизор.",
      "Как редко!",
      "Слишком редко.",
      "Очень редко.",
      "Довольно редко.",
      "Крайне редко.",
      "Не так редко.",
      "Всё реже.",
      "Реже и реже.",
      "Чаще и чаще.",
      "Редко, но метко.",
      "Редко увидишь.",
      "Редкий случай.",
      "Редкая птица.",
      "Редкий гость."
    ]
  },
  {
    "id": "universal_a1_125_ru",
    "word": "много",
    "translations": {
      "en": "many, much, a lot",
      "de": "viel, viele",
      "ar": "كثير، عديد",
      "fr": "beaucoup",
      "it": "molto, molti",
      "ru": "много",
      "es": "mucho, muchos",
      "pl": "dużo, wiele",
      "fa": "زیاد، خیلی"
    },
    "examples": [
      "Много людей.",
      "Много книг.",
      "Много времени.",
      "Много денег.",
      "Много работы.",
      "Много проблем.",
      "Много вопросов.",
      "Много друзей.",
      "Много идей.",
      "У меня много дел.",
      "У тебя много времени?",
      "Очень много.",
      "Слишком много.",
      "Довольно много.",
      "Не так много.",
      "Не очень много.",
      "Сколько много!",
      "Как много!",
      "Много раз.",
      "Много лет.",
      "Много часов.",
      "Много не бывает.",
      "Чем больше, тем лучше.",
      "Много знать — скоро состариться.",
      "Много говорить.",
      "Много работать.",
      "Многого хотеть."
    ]
  },
  {
    "id": "universal_a1_126_ru",
    "word": "мало",
    "translations": {
      "en": "few, little, not much",
      "de": "wenig",
      "ar": "قليل",
      "fr": "peu",
      "it": "poco, pochi",
      "ru": "мало",
      "es": "poco, pocos",
      "pl": "mało",
      "fa": "کم"
    },
    "examples": [
      "Мало людей.",
      "Мало книг.",
      "Мало времени.",
      "Мало денег.",
      "Мало работы.",
      "Мало проблем.",
      "Мало вопросов.",
      "Мало друзей.",
      "Мало идей.",
      "У меня мало времени.",
      "У тебя мало опыта.",
      "Очень мало.",
      "Слишком мало.",
      "Довольно мало.",
      "Не так мало.",
      "Сколько мало!",
      "Как мало!",
      "Мало ли что.",
      "Мало ли кто.",
      "Мало того.",
      "Этого мало.",
      "Мало не покажется.",
      "Мало каши ел.",
      "Меньше да лучше.",
      "Мало говорить.",
      "Мало работать.",
      "Ни много ни мало."
    ]
  },
  {
    "id": "universal_a1_127_ru",
    "word": "хорошо",
    "translations": {
      "en": "well, good, fine",
      "de": "gut",
      "ar": "حسنا، جيد",
      "fr": "bien",
      "it": "bene",
      "ru": "хорошо",
      "es": "bien",
      "pl": "dobrze",
      "fa": "خوب"
    },
    "examples": [
      "Хорошо!",
      "Всё хорошо.",
      "Очень хорошо.",
      "Мне хорошо.",
      "Тебе хорошо?",
      "Как хорошо!",
      "Хорошо живётся.",
      "Хорошо работается.",
      "Хорошо отдыхается.",
      "Говорить хорошо.",
      "Писать хорошо.",
      "Читать хорошо.",
      "Понимать хорошо.",
      "Знать хорошо.",
      "Делать хорошо.",
      "Работать хорошо.",
      "Учиться хорошо.",
      "Петь хорошо.",
      "Танцевать хорошо.",
      "Выглядеть хорошо.",
      "Чувствовать себя хорошо.",
      "Хорошо, что...",
      "Хорошо бы...",
      "Не хорошо.",
      "Совсем хорошо.",
      "Всё будет хорошо.",
      "Хорошо смеётся тот..."
    ]
  },
  {
    "id": "universal_a1_128_ru",
    "word": "плохо",
    "translations": {
      "en": "badly, bad, poorly",
      "de": "schlecht",
      "ar": "سيء، بشكل سيء",
      "fr": "mal, mauvais",
      "it": "male",
      "ru": "плохо",
      "es": "mal",
      "pl": "źle",
      "fa": "بد"
    },
    "examples": [
      "Плохо!",
      "Всё плохо.",
      "Очень плохо.",
      "Мне плохо.",
      "Тебе плохо?",
      "Как плохо!",
      "Плохо живётся.",
      "Плохо работается.",
      "Плохо спится.",
      "Говорить плохо.",
      "Писать плохо.",
      "Читать плохо.",
      "Понимать плохо.",
      "Знать плохо.",
      "Делать плохо.",
      "Работать плохо.",
      "Учиться плохо.",
      "Петь плохо.",
      "Танцевать плохо.",
      "Выглядеть плохо.",
      "Чувствовать себя плохо.",
      "Плохо, что...",
      "Плохо бы...",
      "Не плохо.",
      "Совсем плохо.",
      "Дело плохо.",
      "Плохо дело."
    ]
  },
  {
    "id": "universal_a1_129_ru",
    "word": "быстро",
    "translations": {
      "en": "quickly, fast",
      "de": "schnell",
      "ar": "بسرعة",
      "fr": "vite, rapidement",
      "it": "velocemente, presto",
      "ru": "быстро",
      "es": "rápido, rápidamente",
      "pl": "szybko",
      "fa": "سریع"
    },
    "examples": [
      "Быстро!",
      "Очень быстро.",
      "Слишком быстро.",
      "Довольно быстро.",
      "Не так быстро.",
      "Как быстро!",
      "Идти быстро.",
      "Бежать быстро.",
      "Ехать быстро.",
      "Говорить быстро.",
      "Читать быстро.",
      "Писать быстро.",
      "Думать быстро.",
      "Работать быстро.",
      "Учиться быстро.",
      "Делать быстро.",
      "Решать быстро.",
      "Отвечать быстро.",
      "Понимать быстро.",
      "Запоминать быстро.",
      "Время летит быстро.",
      "Всё проходит быстро.",
      "Быстрее!",
      "Ещё быстрее.",
      "Как можно быстрее.",
      "Побыстрее.",
      "Тише едешь — дальше будешь."
    ]
  },
  {
    "id": "universal_a1_130_ru",
    "word": "медленно",
    "translations": {
      "en": "slowly",
      "de": "langsam",
      "ar": "ببطء",
      "fr": "lentement",
      "it": "lentamente",
      "ru": "медленно",
      "es": "lentamente, despacio",
      "pl": "wolno, powoli",
      "fa": "آهسته، کند"
    },
    "examples": [
      "Медленно!",
      "Очень медленно.",
      "Слишком медленно.",
      "Довольно медленно.",
      "Не так медленно.",
      "Как медленно!",
      "Идти медленно.",
      "Ехать медленно.",
      "Говорить медленно.",
      "Читать медленно.",
      "Писать медленно.",
      "Думать медленно.",
      "Работать медленно.",
      "Учиться медленно.",
      "Делать медленно.",
      "Решать медленно.",
      "Отвечать медленно.",
      "Понимать медленно.",
      "Запоминать медленно.",
      "Время тянется медленно.",
      "Всё идёт медленно.",
      "Медленнее!",
      "Ещё медленнее.",
      "Помедленнее.",
      "Не спеша.",
      "Полегоньку.",
      "Потихоньку."
    ]
  },
  {
    "id": "universal_a1_131_ru",
    "word": "здесь",
    "translations": {
      "en": "here",
      "de": "hier",
      "ar": "هنا",
      "fr": "ici",
      "it": "qui",
      "ru": "здесь",
      "es": "aquí",
      "pl": "tutaj, tu",
      "fa": "اینجا"
    },
    "examples": [
      "Я здесь.",
      "Ты здесь?",
      "Он здесь.",
      "Она здесь.",
      "Мы здесь.",
      "Вы здесь?",
      "Они здесь.",
      "Здесь холодно.",
      "Здесь тепло.",
      "Здесь хорошо.",
      "Здесь плохо.",
      "Здесь тихо.",
      "Здесь шумно.",
      "Здесь красиво.",
      "Здесь уютно.",
      "Живу здесь.",
      "Работаю здесь.",
      "Учусь здесь.",
      "Стою здесь.",
      "Сижу здесь.",
      "Жду здесь.",
      "Остаюсь здесь.",
      "Вот здесь.",
      "Прямо здесь.",
      "Именно здесь.",
      "Не здесь.",
      "Здесь и сейчас."
    ]
  },
  {
    "id": "universal_a1_132_ru",
    "word": "там",
    "translations": {
      "en": "there",
      "de": "dort, da",
      "ar": "هناك",
      "fr": "là, là-bas",
      "it": "lì, là",
      "ru": "там",
      "es": "allí, ahí",
      "pl": "tam",
      "fa": "آنجا"
    },
    "examples": [
      "Я там.",
      "Ты там?",
      "Он там.",
      "Она там.",
      "Мы там.",
      "Вы там?",
      "Они там.",
      "Там холодно.",
      "Там тепло.",
      "Там хорошо.",
      "Там плохо.",
      "Там тихо.",
      "Там шумно.",
      "Там красиво.",
      "Там уютно.",
      "Живу там.",
      "Работаю там.",
      "Учусь там.",
      "Стою там.",
      "Сижу там.",
      "Жду там.",
      "Был там.",
      "Буду там.",
      "Вон там.",
      "Прямо там.",
      "Не там.",
      "Здесь и там."
    ]
  },
  {
    "id": "universal_a1_133_ru",
    "word": "где",
    "translations": {
      "en": "where",
      "de": "wo",
      "ar": "أين",
      "fr": "où",
      "it": "dove",
      "ru": "где",
      "es": "dónde",
      "pl": "gdzie",
      "fa": "کجا"
    },
    "examples": [
      "Где ты?",
      "Где он?",
      "Где она?",
      "Где мы?",
      "Где вы?",
      "Где они?",
      "Где я?",
      "Где это?",
      "Где дом?",
      "Где школа?",
      "Где работа?",
      "Где книга?",
      "Где ключи?",
      "Где туалет?",
      "Где выход?",
      "Где вход?",
      "Где правда?",
      "Где ответ?",
      "Где-то здесь.",
      "Где-то там.",
      "Где-нибудь.",
      "Не знаю где.",
      "Бог знает где.",
      "Где был?",
      "Где будешь?",
      "Где твой дом?",
      "Скажи мне, где?"
    ]
  },
  {
    "id": "universal_a1_134_ru",
    "word": "когда",
    "translations": {
      "en": "when",
      "de": "wann",
      "ar": "متى",
      "fr": "quand",
      "it": "quando",
      "ru": "когда",
      "es": "cuándo",
      "pl": "kiedy",
      "fa": "کی، وقتی"
    },
    "examples": [
      "Когда ты придёшь?",
      "Когда он приедет?",
      "Когда она позвонит?",
      "Когда мы встретимся?",
      "Когда вы будете?",
      "Когда они придут?",
      "Когда это было?",
      "Когда это будет?",
      "Когда урок?",
      "Когда работа?",
      "Когда экзамен?",
      "Когда праздник?",
      "Когда-то давно.",
      "Когда-нибудь.",
      "Не знаю когда.",
      "Бог знает когда.",
      "Когда был?",
      "Когда будешь?",
      "Когда я был маленьким.",
      "Когда я вырасту.",
      "Когда захочешь.",
      "Когда сможешь.",
      "Когда надо.",
      "Когда не надо.",
      "Тогда, когда.",
      "Всегда, когда.",
      "Скажи мне, когда?"
    ]
  },
  {
    "id": "universal_a1_135_ru",
    "word": "почему",
    "translations": {
      "en": "why",
      "de": "warum",
      "ar": "لماذا",
      "fr": "pourquoi",
      "it": "perché",
      "ru": "почему",
      "es": "por qué",
      "pl": "dlaczego",
      "fa": "چرا"
    },
    "examples": [
      "Почему ты здесь?",
      "Почему он опоздал?",
      "Почему она плачет?",
      "Почему мы ждём?",
      "Почему вы молчите?",
      "Почему они ушли?",
      "Почему это?",
      "Почему так?",
      "Почему нет?",
      "Почему да?",
      "Почему не так?",
      "Почему именно я?",
      "Почему именно сейчас?",
      "Почему-то.",
      "Не знаю почему.",
      "Бог знает почему.",
      "Вот почему.",
      "Потому что.",
      "Потому.",
      "Почему бы и нет?",
      "Почему бы не попробовать?",
      "Объясни почему.",
      "Скажи почему.",
      "Пойми почему.",
      "Узнай почему.",
      "Почему молчишь?",
      "Семь раз почему."
    ]
  },
  {
    "id": "universal_a1_136_ru",
    "word": "как",
    "translations": {
      "en": "how, as",
      "de": "wie",
      "ar": "كيف",
      "fr": "comment",
      "it": "come",
      "ru": "как",
      "es": "cómo",
      "pl": "jak",
      "fa": "چگونه، چطور"
    },
    "examples": [
      "Как дела?",
      "Как ты?",
      "Как он?",
      "Как она?",
      "Как вы?",
      "Как это?",
      "Как так?",
      "Как тебя зовут?",
      "Как называется?",
      "Как сказать?",
      "Как делать?",
      "Как работать?",
      "Как учиться?",
      "Как жить?",
      "Как хорошо!",
      "Как плохо!",
      "Как красиво!",
      "Как интересно!",
      "Как-то так.",
      "Как-нибудь.",
      "Не знаю как.",
      "Вот как.",
      "Так как.",
      "Как будто.",
      "Как только.",
      "Как раз.",
      "Скажи, как?"
    ]
  },
  {
    "id": "universal_a1_137_ru",
    "word": "что",
    "translations": {
      "en": "what, that",
      "de": "was, dass",
      "ar": "ماذا، ما",
      "fr": "quoi, que",
      "it": "che, cosa",
      "ru": "что",
      "es": "qué, que",
      "pl": "co, że",
      "fa": "چه، که"
    },
    "examples": [
      "Что это?",
      "Что там?",
      "Что здесь?",
      "Что делать?",
      "Что сказать?",
      "Что думать?",
      "Что случилось?",
      "Что произошло?",
      "Что ты делаешь?",
      "Что он говорит?",
      "Что она хочет?",
      "Что вы знаете?",
      "Что-то случилось.",
      "Что-нибудь.",
      "Не знаю что.",
      "Вот что.",
      "То что.",
      "Всё что.",
      "Я знаю, что...",
      "Я думаю, что...",
      "Я вижу, что...",
      "Что ни говори.",
      "Что бы ни было.",
      "Что было, то было.",
      "Что делать?",
      "Во что бы то ни стало.",
      "Что-то есть."
    ]
  },
  {
    "id": "universal_a1_138_ru",
    "word": "кто",
    "translations": {
      "en": "who",
      "de": "wer",
      "ar": "من",
      "fr": "qui",
      "it": "chi",
      "ru": "кто",
      "es": "quién",
      "pl": "kto",
      "fa": "که، کی"
    },
    "examples": [
      "Кто ты?",
      "Кто он?",
      "Кто она?",
      "Кто вы?",
      "Кто они?",
      "Кто это?",
      "Кто там?",
      "Кто здесь?",
      "Кто знает?",
      "Кто сказал?",
      "Кто сделал?",
      "Кто виноват?",
      "Кто прав?",
      "Кто пришёл?",
      "Кто ушёл?",
      "Кто-то пришёл.",
      "Кто-нибудь.",
      "Не знаю кто.",
      "Вот кто.",
      "Тот кто.",
      "Всякий кто.",
      "Кто угодно.",
      "Кто как.",
      "Кто куда.",
      "Кто где.",
      "Кто ни есть.",
      "Кто не работает..."
    ]
  },
  {
    "id": "universal_a1_139_ru",
    "word": "да",
    "translations": {
      "en": "yes",
      "de": "ja",
      "ar": "نعم",
      "fr": "oui",
      "it": "sì",
      "ru": "да",
      "es": "sí",
      "pl": "tak",
      "fa": "بله"
    },
    "examples": [
      "Да!",
      "Да, конечно.",
      "Да, точно.",
      "Да, верно.",
      "Да, правильно.",
      "Да, хорошо.",
      "Да, согласен.",
      "Да, понятно.",
      "Да, знаю.",
      "Да, помню.",
      "Да, вижу.",
      "Да, слышу.",
      "Да, могу.",
      "Да, хочу.",
      "Да, буду.",
      "Да или нет?",
      "Да и нет.",
      "Ни да ни нет.",
      "Не то да не то нет.",
      "Да, да, да!",
      "Да ну?",
      "Да ладно!",
      "Да что ты!",
      "Да неужели?",
      "Да разве?",
      "Скажи да.",
      "Ответь да."
    ]
  },
  {
    "id": "universal_a1_140_ru",
    "word": "нет",
    "translations": {
      "en": "no",
      "de": "nein",
      "ar": "لا",
      "fr": "non",
      "it": "no",
      "ru": "нет",
      "es": "no",
      "pl": "nie",
      "fa": "نه"
    },
    "examples": [
      "Нет!",
      "Нет, спасибо.",
      "Нет, не хочу.",
      "Нет, не могу.",
      "Нет, не знаю.",
      "Нет, не помню.",
      "Нет, не вижу.",
      "Нет, не слышу.",
      "Нет, не согласен.",
      "Нет, не верю.",
      "Нет, не понимаю.",
      "Нет, не буду.",
      "Да или нет?",
      "Да и нет.",
      "Ни да ни нет.",
      "Нет, нет, нет!",
      "Нет у меня.",
      "Нет времени.",
      "Нет денег.",
      "Нет желания.",
      "Нет возможности.",
      "Нет проблем.",
      "Нет вопросов.",
      "Ни да ни нет.",
      "Нет и всё.",
      "Скажи нет.",
      "Ответь нет."
    ]
  }
]
